{
  "dataList": [
    {
      "id": "announcer_cheer_30_1",
      "dlg": "即使是最优秀的士兵，若不能人尽其才，也只会无所作為。首先要観察战況。\n战況已掌握。接下来……只需挥剑即可。"
    },
    {
      "id": "announcer_cheer_30_2",
      "dlg": "主公对你们寄予厚望。全力以赴吧。\n呵。主公不会因些微失誤就責難你们，所以从容応对即可。"
    },
    {
      "id": "announcer_specialcheer_30_1",
      "dlg": "情況不妙啊。\n照這样突破過去就没問題了。\n……你認真的吗？"
    },
    {
      "id": "announcer_specialcheer_30_2",
      "dlg": "嗯。既然前路已被陰影笼罩，就必須寻覓一线光明。\n“危机”這个詞非要這么説吗？\n……嗯，這个比喻对你来説有点難了吗？"
    },
    {
      "id": "announcer_enemy_break_30_1",
      "dlg": "敌人就像醉酒的浪子般狼狈不堪，若想把握胜机，就在此时。"
    },
    {
      "id": "announcer_ally_break_30_1",
      "dlg": "出现破绽了啊。要去帮忙吗？\n雖然加以利用才是上策……\n但若是主公的話，応該会選择帮助他们吧。\n……好吧。当务之急是照顧伤员。"
    },
    {
      "id": "announcer_killenemy_30_1",
      "dlg": "雖算不上扭転大局……但此举依然可圏可点。"
    },
    {
      "id": "announcer_ally_dead_30_1",
      "dlg": "……這可真是失策。\n用简易保存绷带包起来吧。"
    },
    {
      "id": "announcer_enemy_adv_30_1",
      "dlg": "我……竟在謀略上落了下風吗？\n鸿園地大物博，人才济济。对策之計亦如是。\n……是怎么能把正确的話説得那么討人厌的呢。\n遠不如你。"
    },
    {
      "id": "announcer_ally_adv_30_1",
      "dlg": "形势雖对我们有利，可一旦骄傲自满，便会被逆転。\n……所以你到底要我怎样？\n保持警惕……非要我特地説出口才能明白吗？"
    },
    {
      "id": "announcer_ally_advex_30_1",
      "dlg": "……眼中仍燃烧着斗誌啊。\n真的要付諸行动吗。若真如此，那么此战之胜，便不在天命，而在諸位之誌了。"
    },
    {
      "id": "announcer_danger_30_1",
      "dlg": "此刻如立于万丈深渊之上。\n然，離终点僅剰几步之遙。唯有尽力而為，方可不留遺憾。"
    },
    {
      "id": "announcer_enemy_specialskill_30_1",
      "dlg": "气势雖足，但意図昭然若揭。实乃下策。\n切忌掉以軽心，子貢。"
    },
    {
      "id": "announcer_enemy_specialgimmick_30_1",
      "dlg": "真是妙計。然而定有破解之法。\n倘若无法領悟其中関键，那便如風中残烛般危在旦夕。"
    },
    {
      "id": "announcer_advatk_physical_30_1",
      "dlg": "……正是如此。"
    },
    {
      "id": "announcer_disadvatk_physical_30_1",
      "dlg": "……是否需要重新調遣兵力？\n若不可避免，那次佳之策便是制定策略。"
    },
    {
      "id": "announcer_advatk_attr_30_1",
      "dlg": "……此計有效。"
    },
    {
      "id": "announcer_disadvatk_attr_30_1",
      "dlg": "徒労之举。\n子路啊，為何要特意提醒如此顕而易见之事？\n……唉。"
    },
    {
      "id": "announcer_enemy_specialbuff_30_1",
      "dlg": "看来对方隠藏的招数终于揭晓了啊。"
    },
    {
      "id": "announcer_enemy_specialdebuff_30_1",
      "dlg": "真是自乱陣脚。既有良机，便趁此巩固胜势罢。"
    },
    {
      "id": "announcer_ally_specialbuff_30_1",
      "dlg": "是失策還是有意為之呢。\n若无法揣测其用意，思考其用途方為上策。"
    },
    {
      "id": "announcer_ally_specialdebuff_30_1",
      "dlg": "对方似乎做了什么手脚。\n仔细観察。看起来這不是能軽易摆脱的魔爪。"
    },
    {
      "id": "announcer_enemy_destroy_30_1",
      "dlg": "嗯。已经折断敌人之翼了啊。"
    },
    {
      "id": "announcer_enemy_destroy_30_2",
      "dlg": "有了顕著的差距啊。\n当然了。我軍的优势将如同滚下斜坡的雪球般不断扩大。"
    },
    {
      "id": "announcer_round_takebigdmg_30_1",
      "dlg": "咳。是敌軍的陥阱吗？\n撤退。我来……\n……不，我還有応对之策。"
    },
    {
      "id": "announcer_round_takebigdmg_30_2",
      "dlg": "莫要气馁。有些东西，得上去碰一碰才能明白。\n有必要這么拼命吗？"
    },
    {
      "id": "announcer_round_givebigdmg_30_1",
      "dlg": "拿下了对方的車和砲吗。此計确实出乎我的意料呢。"
    },
    {
      "id": "announcer_round_givebigdmg_30_2",
      "dlg": "敌人的四肢已被斩断。现在全力進攻吧。"
    },
    {
      "id": "announcer_multikillenemy_30_1",
      "dlg": "哼。会挥剑之人何其多。重要的是其剑是否有道。\n若是中意的話便直説吧，子路啊。面对此等稀世猛将，有何理由吝惜賛美呢。"
    },
    {
      "id": "announcer_equip_30_1",
      "dlg": "我乃主公的謀士兼右臂，子貢。奉主公之命，前来统領你们的部隊。\n……我是子路。"
    }
  ]
}