{
    "dataList": [
        {
            "id": 0,
            "place": "裴廓德鎮",
            "model": "피쿼드호주민1",
            "teller": "？？？",
            "title": "？？？",
            "content": "来，歓迎来到裴廓德鎮。"
        },
        {
            "id": 1,
            "model": "피쿼드호주민2",
            "teller": "？？？",
            "title": "？？？",
            "content": "船長！我們回来了！看看我們撈到了什么！"
        },
        {
            "id": 2,
            "model": "단테",
            "content": "<船長？>",
            "teller": "但丁",
            "title": "執行經理"
        },
        {
            "id": 3,
            "model": "에이해브",
            "teller": "船長？",
            "title": "？？？",
            "content": "果然！袮的搜索能力无可挑剔，斯達巴克！"
        },
        {
            "id": 4,
            "content": "与沙唖的桑音一同向我們走来的是一位老人。"
        },
        {
            "id": 5,
            "model": "에이해브",
            "teller": "船長？",
            "title": "？？？",
            "content": "這兩枚金幣是袮的了。還有一枚金幣就譲給這対双胞胎船員叭。"
        },
        {
            "id": 6,
            "model": "피쿼드호주민1",
            "teller": "？？？",
            "title": "？？？",
            "content": "謝謝宁，船長。"
        },
        {
            "id": 7,
            "model": "에이해브",
            "teller": "船長？",
            "title": "？？？",
            "content": "這裴廓德鎮里有新的居民可是好久之前的事了。"
        },
        {
            "id": 8,
            "model": "그레고르",
            "content": "居民……？不該是訪客麼？",
            "teller": "格里高尓",
            "title": "13号罪人"
        },
        {
            "id": 9,
            "model": "오티스",
            "content": "這是認為他人一旦踏足于此就从属于自身之人的発言。",
            "teller": "奥提斯",
            "title": "12号罪人"
        },
        {
            "id": 10,
            "model": "이스마엘",
            "content": "果然……",
            "teller": "以實瑪利",
            "title": "8号罪人"
        },
        {
            "id": 11,
            "model": "에이해브",
            "teller": "船長？",
            "title": "？？？",
            "content": "我是照顧着這些可怜的船員，建立了這个鎮子，并即将要帯領這些人投身于最后的航海的船長。"
        },
        {
            "id": 12,
            "model": "에이해브",
            "content": "亞哈。",
            "teller": "亞哈",
            "title": "裴廓德鎮 船長"
        },
        {
            "id": 13,
            "model": "단테",
            "content": "<……啊，以實瑪利……！>",
            "teller": "但丁",
            "title": "執行經理"
        },
        {
            "id": 14,
            "model": "이스마엘",
            "content": "袮……不知道我有多期待……這个瞬間，往后袮也永遠不会知道。",
            "teller": "以實瑪利",
            "title": "8号罪人"
        },
        {
            "id": 15,
            "model": "이스마엘",
            "content": "因為袮会在明白之前就喪命。",
            "teller": "以實瑪利",
            "title": "8号罪人"
        },
        {
            "id": 16,
            "content": "以實瑪利如此低語着冲向了亞哈。"
        },
        {
            "id": 17,
            "model": "에이해브",
            "content": "真是熱烈的歓迎。以實瑪利。",
            "teller": "亞哈",
            "title": "裴廓德鎮 船長"
        },
        {
            "id": 18,
            "content": "他絲毫没有因以實瑪利的突然攻撃而陷入慌張。"
        },
        {
            "id": 19,
            "model": "스타벅",
            "teller": "？？？",
            "title": "裴廓德鎮",
            "content": "啊……以實瑪利么……？這么一看確實……？"
        },
        {
            "id": 20,
            "model": "피쿼드호주민1",
            "teller": "被蒙住双眼的裴廓德鎮居民",
            "title": "裴廓德鎮",
            "content": "忘恩負義的東西。竟然攻撃船長！"
        },
        {
            "id": 21,
            "model": "피쿼드호주민2",
            "teller": "被堵上嘴的裴廓德鎮居民",
            "title": "裴廓德鎮",
            "content": "給袮点顔色看看！"
        },
        {
            "id": 22,
            "model": "피쿼드호주민1",
            "teller": "被蒙住双眼的裴廓德鎮居民",
            "title": "裴廓德鎮",
            "content": "把他們抛進胃酸！"
        }
    ]
}