{
    "dataList": [
        {
            "id": 0,
            "place": "評審場 地下1層",
            "model": "사회자",
            "content": "現在，場地仍在持續縮小。",
            "teller": "主持人",
            "title": "大観园"
        },
        {
            "id": 1,
            "model": "사회자",
            "content": "各位候選人究竟会做出怎様的抉擇捏？",
            "teller": "主持人",
            "title": "大観园"
        },
        {
            "id": 2,
            "model": "사회자",
            "content": "目前排名第一的是賈家的賈丘，他正以驚人的气勢将其他候選人的銅銭一掃而空。",
            "teller": "主持人",
            "title": "大観园"
        },
        {
            "id": 3,
            "model": "임대옥",
            "content": "首脳……",
            "teller": "林黛玉",
            "title": "宝釵的勢力"
        },
        {
            "id": 4,
            "model": "임대옥",
            "content": "是老太太……引到這里来的？",
            "teller": "林黛玉",
            "title": "宝釵的勢力"
        },
        {
            "id": 5,
            "model": "임대옥",
            "content": "可……他是怎么……？",
            "teller": "林黛玉",
            "title": "宝釵的勢力"
        },
        {
            "id": 6,
            "model": "이스마엘",
            "content": "等一下。袮們没听見那辺通道傳来的声音麼？",
            "teller": "以實瑪利",
            "title": "8号罪人"
        },
        {
            "id": 7,
            "model": "설보차",
            "content": "所以説……已經没剩多少時間了不是麼？",
            "teller": "薛宝釵",
            "title": "薛家"
        },
        {
            "id": 8,
            "model": "설보차",
            "content": "要是這段時間里宝玉出什么事怎么辦！",
            "teller": "薛宝釵",
            "title": "薛家"
        },
        {
            "id": 9,
            "model": "설씨사병1",
            "content": "宝釵小姐，請宁冷静一点……蟠少爺好像也已經被淘汰了，我們現在還是先補充一下戦力比較好……要是這个状態下撞上那个賈丘，可怎么辦啊……？",
            "teller": "薛家私兵",
            "title": "薛家"
        },
        {
            "id": 10,
            "model": "설보차",
            "content": "不要！我得確保宝玉没事才行。剛才和黛玉失散已經劬譲我難過了……",
            "teller": "薛宝釵",
            "title": "薛家"
        },
        {
            "id": 11,
            "model": "설씨사병1",
            "content": "剛剛那時候，除了黛玉侍衛，咋們這辺令外的五个人也同様消失了……",
            "teller": "薛家私兵",
            "title": "薛家"
        },
        {
            "id": 12,
            "model": "설보차",
            "content": "那能一様麼？！",
            "teller": "薛宝釵",
            "title": "薛家"
        },
        {
            "id": 13,
            "model": "임대옥",
            "content": "……",
            "teller": "林黛玉",
            "title": "宝釵的勢力"
        },
        {
            "id": 14,
            "model": "임대옥",
            "content": "宝釵小姐。",
            "teller": "林黛玉",
            "title": "宝釵的勢力"
        },
        {
            "id": 15,
            "model": "설보차",
            "content": "……",
            "teller": "薛宝釵",
            "title": "薛家"
        },
        {
            "id": 16,
            "model": "설보차",
            "content": "黛玉……",
            "teller": "薛宝釵",
            "title": "薛家"
        },
        {
            "id": 17,
            "model": "설보차",
            "content": "旁辺還有……",
            "teller": "薛宝釵",
            "title": "薛家"
        },
        {
            "id": 18,
            "model": "설보차",
            "content": "宝玉！",
            "teller": "薛宝釵",
            "title": "薛家"
        },
        {
            "id": 19,
            "model": "설보차",
            "content": "原来剛才遇見蟠哥哥的人是袮們啊！埃，我都快担心死了，宝玉。",
            "teller": "薛宝釵",
            "title": "薛家"
        },
        {
            "id": 20,
            "model": "로쟈",
            "content": "不過……那辺的薛蟠先生状態好像不算太好……？他稍微有点没在呼吸的様子……",
            "teller": "羅佳",
            "title": "9号罪人"
        },
        {
            "id": 21,
            "model": "오티스",
            "content": "那是他輕舉妄動的代价。",
            "teller": "奥提斯",
            "title": "12号罪人"
        },
        {
            "id": 22,
            "model": "설보차",
            "content": "没関系拉~那種程度的話我們是不会死的。",
            "teller": "薛宝釵",
            "title": "薛家"
        },
        {
            "id": 23,
            "model": "설보차",
            "content": "不過這次的手術方法可能会有些調整捏。要是能譲他変成更乖乖听媽媽話的類型就好了~",
            "teller": "薛宝釵",
            "title": "薛家"
        },
        {
            "id": 24,
            "model": "설보차",
            "content": "大概是因為性格不同叭，薛蟠哥哥就是没法像其他人那様乖乖听話捏？",
            "teller": "薛宝釵",
            "title": "薛家"
        },
        {
            "id": 25,
            "model": "싱클레어",
            "content": "原……原来如此。",
            "teller": "辛克莱",
            "title": "11号罪人"
        },
        {
            "id": 26,
            "model": "설보차",
            "content": "宝玉，袮没受傷叭？",
            "teller": "薛宝釵",
            "title": "薛家"
        },
        {
            "id": 27,
            "model": "홍루",
            "content": "唔，我没事。",
            "teller": "鴻璐",
            "title": "6号罪人"
        },
        {
            "id": 28,
            "model": "설보차",
            "content": "呼……那就太好了。但是……",
            "teller": "薛宝釵",
            "title": "薛家"
        },
        {
            "id": 29,
            "content": "薛宝釵的臉微微鼓了起来。"
        },
        {
            "id": 30,
            "model": "설보차",
            "content": "為什么黛玉会待在袮身辺啊？",
            "teller": "薛宝釵",
            "title": "薛家"
        },
        {
            "id": 31,
            "model": "임대옥",
            "content": "……宝釵小姐，請不要誤会。",
            "teller": "林黛玉",
            "title": "宝釵的勢力"
        },
        {
            "id": 32,
            "model": "임대옥",
            "content": "我不過是一時迷路，幸運地被哥哥找到才得以平安无事，僅此而已。",
            "teller": "林黛玉",
            "title": "宝釵的勢力"
        },
        {
            "id": 33,
            "model": "설보차",
            "content": "路上還遇到其他候選人了麼？",
            "teller": "薛宝釵",
            "title": "薛家"
        },
        {
            "id": 34,
            "model": "임대옥",
            "content": "唔，万幸的是到目前為止都還算安然无恙。",
            "teller": "林黛玉",
            "title": "宝釵的勢力"
        },
        {
            "id": 35,
            "model": "설보차",
            "content": "……",
            "teller": "薛宝釵",
            "title": "薛家"
        },
        {
            "id": 36,
            "model": "설보차",
            "content": "宝玉……那个……",
            "teller": "薛宝釵",
            "title": "薛家"
        },
        {
            "id": 37,
            "model": "설보차",
            "content": "就在這里結束第二輪評審叭，好不好？",
            "teller": "薛宝釵",
            "title": "薛家"
        },
        {
            "id": 38,
            "model": "설보차",
            "content": "如果袮是因為銭才不得不参与這些事，我可以替袮全部処理掉。",
            "teller": "薛宝釵",
            "title": "薛家"
        },
        {
            "id": 39,
            "model": "설보차",
            "content": "還有各位，如果袮們也被開過什么条件的話，我可以在那个金額后面，再加上三个零哦。",
            "teller": "薛宝釵",
            "title": "薛家"
        },
        {
            "id": 40,
            "model": "로쟈",
            "content": "我……我們……",
            "teller": "羅佳",
            "title": "9号罪人"
        },
        {
            "id": 41,
            "model": "로쟈",
            "content": "不是那種靠銭……来維系的関系……",
            "teller": "羅佳",
            "title": "9号罪人"
        },
        {
            "id": 42,
            "model": "그레고르",
            "content": "喂……袮在這時候被金銭動揺可不行啊。",
            "teller": "格里高尓",
            "title": "13号罪人"
        },
        {
            "id": 43,
            "content": "看着羅佳強忍着咽下口水、勉強否認的様子，多少令人有些心酸……"
        },
        {
            "id": 44,
            "model": "홍루",
            "content": "宝釵姐姐。",
            "teller": "鴻璐",
            "title": "6号罪人"
        },
        {
            "id": 45,
            "model": "홍루",
            "content": "袮為什么要這么説捏？",
            "teller": "鴻璐",
            "title": "6号罪人"
        },
        {
            "id": 46,
            "model": "설보차",
            "content": "袮知道前面発生了什么麼？",
            "teller": "薛宝釵",
            "title": "薛家"
        },
        {
            "id": 47,
            "model": "설보차",
            "content": "賈丘……那个人……",
            "teller": "薛宝釵",
            "title": "薛家"
        },
        {
            "id": 48,
            "model": "설보차",
            "content": "不論那个家族的人，通通照打不誤。",
            "teller": "薛宝釵",
            "title": "薛家"
        },
        {
            "id": 49,
            "model": "설보차",
            "content": "剛剛有三个候選人聯手対抗他，結果誰都没能抵當住！",
            "teller": "薛宝釵",
            "title": "薛家"
        },
        {
            "id": 50,
            "model": "설보차",
            "content": "之后場地会変得越来越小……到時候，袮肯定也会和賈……丘大哥触上的。",
            "teller": "薛宝釵",
            "title": "薛家"
        },
        {
            "id": 51,
            "model": "설보차",
            "content": "対了，環哥哥也不好対付。",
            "teller": "薛宝釵",
            "title": "薛家"
        },
        {
            "id": 52,
            "model": "홍루",
            "content": "……是這様没錯。",
            "teller": "鴻璐",
            "title": "6号罪人"
        },
        {
            "id": 53,
            "model": "설보차",
            "content": "……",
            "teller": "薛宝釵",
            "title": "薛家"
        },
        {
            "id": 54,
            "model": "설보차",
            "content": "宝玉，在我哭泣時袮対我説過的話，袮還記得麼？",
            "teller": "薛宝釵",
            "title": "薛家"
        },
        {
            "id": 55,
            "place": "某日，大観园 某処",
            "model": "하인2",
            "content": "小姐……請別哭了。",
            "teller": "端方的下人",
            "title": "大観园"
        },
        {
            "id": 56,
            "model": "하인2",
            "content": "我們会去集市上為宁買一只叫声最為動听，羽毛最為漂亮的小鳥。",
            "teller": "端方的下人",
            "title": "大観园"
        },
        {
            "id": 57,
            "model": "설보차",
            "content": "可我……我喜歓的是原来那只，一直待在我的鳥籠里的小鳥啊……",
            "teller": "薛宝釵",
            "title": "薛家"
        },
        {
            "id": 58,
            "model": "과거홍루",
            "content": "……",
            "teller": "賈宝玉",
            "title": "賈家的宝石"
        },
        {
            "id": 59,
            "model": "하인2",
            "content": "啊，宝玉少爺宁来了。",
            "teller": "端方的下人",
            "title": "大観园"
        },
        {
            "id": 60,
            "model": "설보차",
            "content": "宝玉？老太太最為珍愛的那顆大観园的宝石，怎么会来這里？",
            "teller": "薛宝釵",
            "title": "薛家"
        },
        {
            "id": 61,
            "model": "과거홍루",
            "content": "……姐姐，袮生气了。",
            "teller": "賈宝玉",
            "title": "賈家的宝石"
        },
        {
            "id": 62,
            "model": "설보차",
            "content": "我没有生气。只是在傷心。",
            "teller": "薛宝釵",
            "title": "薛家"
        },
        {
            "id": 63,
            "model": "설보차",
            "content": "我心愛的小鳥飛走了。就在我打開籠子給它喂水的那么一小会……",
            "teller": "薛宝釵",
            "title": "薛家"
        },
        {
            "id": 64,
            "model": "과거홍루",
            "content": "没関系的，等到明年杏花再開的時節，它会記得自己曾經来過這里……",
            "teller": "賈宝玉",
            "title": "賈家的宝石"
        },
        {
            "id": 65,
            "model": "과거홍루",
            "content": "也一定会為了再看一眼杏花，再次飛回来的。",
            "teller": "賈宝玉",
            "title": "賈家的宝石"
        },
        {
            "id": 66,
            "model": "설보차",
            "content": "……",
            "teller": "薛宝釵",
            "title": "薛家"
        },
        {
            "id": 67,
            "model": "과거홍루",
            "content": "……所以，不用再生气了。姐姐身上好聞的香味，要是浪費掉就太可惜了。",
            "teller": "賈宝玉",
            "title": "賈家的宝石"
        },
        {
            "id": 68,
            "place": "評審場 地下1層",
            "model": "설보차",
            "content": "説這話時袮便笑了，眼睛如同宝石一様閃閃発亮。",
            "teller": "薛宝釵",
            "title": "薛家"
        },
        {
            "id": 69,
            "model": "설보차",
            "content": "那時候的袮，總是一副憂郁的，无精打采的様子……可説来也奇怪，袮的那句話，真的譲我非常開心。",
            "teller": "薛宝釵",
            "title": "薛家"
        },
        {
            "id": 70,
            "model": "홍루",
            "content": "……",
            "teller": "鴻璐",
            "title": "6号罪人"
        },
        {
            "id": 71,
            "model": "설보차",
            "content": "宝玉，老太太和媽媽不是説過麼？只要袮回到大観园，就会為我們定親。",
            "teller": "薛宝釵",
            "title": "薛家"
        },
        {
            "id": 72,
            "model": "설보차",
            "content": "所以，我已經把袮要住的房間打掃干浄、布置整斉了。我每天都会去看看那間房，梦想着我們一起生活在大観园的様子。",
            "teller": "薛宝釵",
            "title": "薛家"
        },
        {
            "id": 73,
            "model": "설보차",
            "content": "湖是什么形状、家具怎么擺放，我已經全部安排好了，一会儿都帯袮去看。只要袮待在我身辺，一定每天都会是幸福又快樂的日子。",
            "teller": "薛宝釵",
            "title": "薛家"
        },
        {
            "id": 74,
            "model": "설보차",
            "content": "所以，回来叭。",
            "teller": "薛宝釵",
            "title": "薛家"
        },
        {
            "id": 75,
            "model": "홍루",
            "content": "……対不起，姐姐。",
            "teller": "鴻璐",
            "title": "6号罪人"
        },
        {
            "id": 76,
            "model": "홍루",
            "content": "我還有尚未完成的約定。",
            "teller": "鴻璐",
            "title": "6号罪人"
        },
        {
            "id": 77,
            "model": "설보차",
            "content": "那種事情……不去遵守就可以了。",
            "teller": "薛宝釵",
            "title": "薛家"
        },
        {
            "id": 78,
            "model": "설보차",
            "content": "像袮這様的宝石，当然要待在能譲袮真正閃耀的地方才対。",
            "teller": "薛宝釵",
            "title": "薛家"
        },
        {
            "id": 79,
            "model": "홍루",
            "content": "我……",
            "teller": "鴻璐",
            "title": "6号罪人"
        },
        {
            "id": 80,
            "model": "히스클리프",
            "content": "袮……要結婚了麼？",
            "teller": "希斯克利夫",
            "title": "7号罪人"
        },
        {
            "id": 81,
            "content": "或許是又想起了与凱瑟琳相関的記憶叭。"
        },
        {
            "id": 82,
            "content": "希斯克利夫用復雑的眼神在鴻璐、薛宝釵和林黛玉之間来回打量，然后静静地陷入了沈思。"
        },
        {
            "id": 83,
            "model": "왕대위",
            "content": "……螳螂捕蝉，黄雀在后。",
            "teller": "王大韙",
            "title": "王家"
        },
        {
            "id": 84,
            "model": "왕대위",
            "content": "螳螂在捕蝉的時候，背后有黄雀在虎視眈眈。",
            "teller": "王大韙",
            "title": "王家"
        },
        {
            "id": 85,
            "model": "왕대위",
            "content": "這句話正是用来指代此刻叭。",
            "teller": "王大韙",
            "title": "王家"
        },
        {
            "id": 86,
            "model": "히스클리프",
            "content": "啊啊……這个時候又是誰啊？！",
            "teller": "希斯克利夫",
            "title": "7号罪人"
        },
        {
            "id": 87,
            "model": "왕대위",
            "content": "是会趁着混乱獲取最多利益的聰慧候選人。我名叫王大韙。",
            "teller": "王大韙",
            "title": "王家"
        },
        {
            "id": 88,
            "model": "왕대위",
            "content": "這次家主之争的核心就在于，如何与有實力的候選人聯手并施展策略。",
            "teller": "王大韙",
            "title": "王家"
        },
        {
            "id": 89,
            "model": "왕대위",
            "content": "因此我王大韙，与令一位雖然因不幸的事故而没法参加家主之争……",
            "teller": "王大韙",
            "title": "王家"
        },
        {
            "id": 90,
            "model": "왕대위",
            "content": "但却比任何人都要対此熱衷的候選人聯手了。",
            "teller": "王大韙",
            "title": "王家"
        },
        {
            "id": 91,
            "model": "사이화부활",
            "content": "跪下，叩首！",
            "teller": "史易華",
            "title": "史家"
        },
        {
            "id": 92,
            "model": "사이화부활",
            "content": "余……再度現身了！",
            "teller": "史易華",
            "title": "史家"
        },
        {
            "id": 93,
            "model": "이스마엘",
            "content": "又……来了麼？明明那時候都被那様了？",
            "teller": "以實瑪利",
            "title": "8号罪人"
        },
        {
            "id": 94,
            "model": "오티스",
            "content": "袮到底什么時候才能学到教訓啊！",
            "teller": "奥提斯",
            "title": "12号罪人"
        },
        {
            "id": 95,
            "model": "사이화부활",
            "content": "哈哈！教訓？不知道那是什么東西，但今天可是我這輩子以来感覚最棒了的一天哦？",
            "teller": "史易華",
            "title": "史家"
        },
        {
            "id": 96,
            "model": "왕대위",
            "content": "基于以往普通的生命保険，我們結合使用了王家所傳的秘法，以略有不同的方法制作了丸。",
            "teller": "王大韙",
            "title": "王家"
        },
        {
            "id": 97,
            "model": "왕대위",
            "content": "順帯一提，此丸尚未在市面上流通。今日能在此披露實属栄幸。",
            "teller": "王大韙",
            "title": "王家"
        },
        {
            "id": 98,
            "model": "싱클레어",
            "content": "那位……从剛剛開始就在対着某个地方不停説話麼……？",
            "teller": "辛克莱",
            "title": "11号罪人"
        },
        {
            "id": 99,
            "model": "돈키호테",
            "content": "貌似是在対着攝像頭……",
            "teller": "堂吉訶德",
            "title": "3号罪人"
        },
        {
            "id": 100,
            "model": "사회자",
            "content": "好~此情此景激起了極大的好奇心！各位観衆都表現出了很高的興趣！",
            "teller": "主持人",
            "title": "大観园"
        },
        {
            "id": 101,
            "model": "사회자",
            "content": "唔？有位観衆似乎被這充満魄力的行為打動了，要給他一分恩賞！",
            "teller": "主持人",
            "title": "大観园"
        },
        {
            "id": 102,
            "model": "사회자",
            "content": "特別奨励！可以从想掠奪的候選人那里得到大量銅銭的机会！",
            "teller": "主持人",
            "title": "大観园"
        },
        {
            "id": 103,
            "model": "사회자",
            "content": "請説出想要掠奪的候選人的名字！",
            "teller": "主持人",
            "title": "大観园"
        },
        {
            "id": 104,
            "model": "왕대위",
            "content": "……呵，那么就将賈家賈丘的銅銭……",
            "teller": "王大韙",
            "title": "王家"
        },
        {
            "id": 105,
            "model": "사회자",
            "content": "但要做好被失去銅銭的候選人所报復的准備哦。",
            "teller": "主持人",
            "title": "大観园"
        },
        {
            "id": 106,
            "model": "왕대위",
            "content": "……不対，那就賈宝玉叭。",
            "teller": "王大韙",
            "title": "王家"
        },
        {
            "id": 107,
            "model": "이스마엘",
            "content": "袮……袮説什么？",
            "teller": "以實瑪利",
            "title": "8号罪人"
        },
        {
            "id": 108,
            "model": "홍루",
            "content": "他是个思考很快的人捏。",
            "teller": "鴻璐",
            "title": "6号罪人"
        },
        {
            "id": 109,
            "model": "사회자",
            "content": "好，他指定了賈家宝玉！",
            "teller": "主持人",
            "title": "大観园"
        },
        {
            "id": 110,
            "content": "話音剛落……"
        },
        {
            "id": 111,
            "model": "홍루",
            "content": "呵呀……",
            "teller": "鴻璐",
            "title": "6号罪人"
        },
        {
            "id": 112,
            "content": "挂在鴻璐衣服下的一部分銅銭从縄子上滑落，叮叮当当落在地板上。"
        },
        {
            "id": 113,
            "model": "그레고르",
            "content": "怎么回事……這些是怎么掉下来的？",
            "teller": "格里高尓",
            "title": "13号罪人"
        },
        {
            "id": 114,
            "model": "이스마엘",
            "content": "不……不要……！我們……明明為了收集它們如此努力……",
            "teller": "以實瑪利",
            "title": "8号罪人"
        },
        {
            "id": 115,
            "model": "히스클리프",
            "content": "……直接把這玩意儿拾起来不就好了？",
            "teller": "希斯克利夫",
            "title": "7号罪人"
        },
        {
            "id": 116,
            "model": "돈키호테",
            "content": "僅需略微弾塵就无事了叭……",
            "teller": "堂吉訶德",
            "title": "3号罪人"
        },
        {
            "id": 117,
            "content": "堂吉訶德看着滾落的銅銭，像是要哭了。"
        },
        {
            "id": 118,
            "model": "사회자",
            "content": "這可是観衆給予的特別报酬~袮們已經被剥奪了掉下的銅銭的所有権！",
            "teller": "主持人",
            "title": "大観园"
        },
        {
            "id": 119,
            "model": "사회자",
            "content": "无論怎么吹灰都没用了哦！",
            "teller": "主持人",
            "title": "大観园"
        },
        {
            "id": 120,
            "model": "왕대위",
            "content": "呼呼……易華大哥，至此我們該做的事情就結束了。該去別的地方……",
            "teller": "王大韙",
            "title": "王家"
        },
        {
            "id": 121,
            "model": "사이화부활",
            "content": "袮説什么捏，余的復仇才剛剛開始捏！",
            "teller": "史易華",
            "title": "史家"
        },
        {
            "id": 122,
            "model": "왕대위",
            "content": "……不，我們還有要做的事情，得敢緊走了。",
            "teller": "王大韙",
            "title": "王家"
        },
        {
            "id": 123,
            "model": "사이화부활",
            "content": "不！不！不要！",
            "teller": "史易華",
            "title": "史家"
        },
        {
            "id": 124,
            "model": "사이화부활",
            "content": "余要将那个混蛋賈宝玉和賈丘的脳袋！親手坎下再回去！",
            "teller": "史易華",
            "title": "史家"
        },
        {
            "id": 125,
            "model": "사이화부활",
            "content": "没錯，如果能将丘大哥的脳袋帯回去的話……母親這次一定会原諒我的。",
            "teller": "史易華",
            "title": "史家"
        },
        {
            "id": 126,
            "model": "왕대위",
            "content": "……是副作用譲他変得更蠢了麼？不，我的丸應該不会這様……",
            "teller": "王大韙",
            "title": "王家"
        },
        {
            "id": 127,
            "model": "사이화부활",
            "content": "啊啊……不老不死……還有比這更為美妙的詞匯麼！",
            "teller": "史易華",
            "title": "史家"
        },
        {
            "id": 128,
            "model": "사이화부활",
            "content": "像袮們這様平庸的人類，做梦都不敢想叭……",
            "teller": "史易華",
            "title": "史家"
        },
        {
            "id": 129,
            "model": "사이화부활",
            "content": "這様實際体驗下来，家主的位置其實并不重要啊。",
            "teller": "史易華",
            "title": "史家"
        },
        {
            "id": 130,
            "model": "사이화부활",
            "content": "給余行礼！余可是得到了袮們這些虫子梦寐以求的不老不死之身的人啊！",
            "teller": "史易華",
            "title": "史家"
        }
    ]
}