{
  "dataList": [
    {
      "id": 0,
      "place": "里恩的住处",
      "model": "뉴키라",
      "content": "看他们那么拼命地拦着，可門後面也没什么大不了的嘛？"
    },
    {
      "id": 1,
      "model": "그레고르",
      "content": "就是啊。看起来就是間普通的住宅嘛。"
    },
    {
      "id": 2,
      "model": "뉴키라",
      "content": "咳咳……哇，這么多灰。咱知道打扫卫生是很麻烦，但這也太過分了。"
    },
    {
      "id": 3,
      "content": "从四处堆积的黒色尘埃以及布满污痕的壁纸上看……這里好像已经很久没有人居住了。"
    },
    {
      "id": 4,
      "model": "싱클레어",
      "content": "看来這里曾经住過小孩呢。"
    },
    {
      "id": 5,
      "model": "싱클레어",
      "content": "不管是画，還是玩偶……看样子都被扔在這儿好久了。"
    },
    {
      "id": 6,
      "model": "싱클레어",
      "content": "是发生過什么糟糕的事情吗？"
    },
    {
      "id": 7,
      "model": "뉴키라",
      "content": "是屋里出了啥事就逃走了吧？之後就再也没有回来過。"
    },
    {
      "id": 8,
      "model": "히스클리프",
      "content": "是啊。門也開着，一只靴子也丢在那里。"
    },
    {
      "id": 9,
      "model": "이스마엘",
      "content": "譲人逃出家門，并且這么久都没法回来吗……"
    },
    {
      "id": 10,
      "model": "이스마엘",
      "content": "能想到的理由太多，反而想象不出来了。"
    },
    {
      "id": 12,
      "model": "단테",
      "content": "<良秀。你在找什么吗？>"
    },
    {
      "id": 13,
      "model": "료슈",
      "content": "……对。但好像不在這里。"
    },
    {
      "id": 14,
      "model": "료슈",
      "content": "相框里的照片全都被烧焦了，所有類似文件的东西都被撕成了碎片。"
    },
    {
      "id": 15,
      "model": "료슈2",
      "content": "呼……乱七八糟的，跟我的記忆一样啊。"
    },
    {
      "id": 16,
      "model": "료슈",
      "content": "那家伙。没有逃到這里来……吗。"
    },
    {
      "id": 17,
      "content": "食指父輩，里恩。在受重伤後，利用走廊隠匿身形逃走了。"
    },
    {
      "id": 18,
      "content": "他如果還活着的話，也許有朝一日会再次盯上良秀……"
    },
    {
      "id": 19,
      "content": "但不知為何，一想到那人最後的样子……我总感覚他再也不会出现在良秀面前了。"
    },
    {
      "id": 20,
      "model": "료슈",
      "content": "這是……"
    },
    {
      "id": 21,
      "model": "단테",
      "content": "<你認得這幅画吗？>"
    },
    {
      "id": 22,
      "content": "因為……良秀今天一遇到什么总能唤起她的回忆，所以我期待着她這次也能想起些什么……"
    },
    {
      "id": 23,
      "content": "良秀軽軽地搖了搖头。"
    },
    {
      "id": 24,
      "model": "료슈9장",
      "content": "……不。"
    },
    {
      "id": 25,
      "model": "료슈9장",
      "content": "我想不起来。"
    }
  ]
}