{
    "dataList": [
        {
            "id": 0,
            "place": "T公司小巷 某処",
            "content": "冲突剛剛緩解了一些，立刻又有不同着装的T公司員工靠近了罪人們。"
        },
        {
            "id": 1,
            "model": "T사4등급",
            "teller": "4級征收人員",
            "title": "T公司",
            "content": "……"
        },
        {
            "id": 2,
            "model": "오티스",
            "content": "……那群家夥的頭領麼？",
            "teller": "奥提斯",
            "title": "12号罪人"
        },
        {
            "id": 3,
            "model": "이상",
            "content": "就算等級再高，他也只是T公司的員工，并不是那種概念……",
            "teller": "李箱",
            "title": "1号罪人"
        },
        {
            "id": 4,
            "model": "이상",
            "content": "与他們継續争執下去的話，会発展成対抗整个T公司的状况……",
            "teller": "李箱",
            "title": "1号罪人"
        },
        {
            "id": 5,
            "model": "T사4등급",
            "teller": "4級征收人員",
            "title": "T公司",
            "content": "立刻停止戦斗。"
        },
        {
            "id": 6,
            "model": "T사4등급",
            "teller": "4級征收人員",
            "title": "T公司",
            "content": "如若拒絶合作，所有在場人員将被視為敵対勢力并受到武力鎮圧……"
        },
        {
            "id": 7,
            "model": "료슈",
            "content": "呵呵……変得有趣起来了。",
            "teller": "良秀",
            "title": "4号罪人"
        },
        {
            "id": 8,
            "model": "로쟈",
            "content": "啊……這様的話……",
            "teller": "羅佳",
            "title": "9号罪人"
        },
        {
            "id": 9,
            "model": "단테",
            "content": "<是時候輪到維吉里烏斯瞪着他那可怕的眼睛……从那里……>",
            "teller": "但丁",
            "title": "執行經理"
        },
        {
            "id": 10,
            "model": "뫼르소",
            "content": "出現了。",
            "teller": "默尓索",
            "title": "5号罪人"
        },
        {
            "id": 11,
            "model": "그레고르",
            "content": "明明几天前還覚得和向導先生之間和諧的氛圍能維持下去……可現在却覚得那是很遥遠的事了。",
            "teller": "格里高尓",
            "title": "13号罪人"
        },
        {
            "id": 12,
            "model": "로쟈",
            "content": "別用那種眼神訂着我們了，袮听我們解釋。真的是冤枉啊~這人可是突然要我們交出100億眼啊~",
            "teller": "羅佳",
            "title": "9号罪人"
        },
        {
            "id": 13,
            "model": "T사2등급",
            "teller": "2級征收人員",
            "title": "T公司",
            "content": "共100億4000万眼。"
        },
        {
            "id": 14,
            "model": "그레고르",
            "content": "袮是在放録音麼？怎么老是説同様的話……",
            "teller": "格里高尓",
            "title": "13号罪人"
        },
        {
            "id": 15,
            "model": "로쟈",
            "content": "関鍵是，怎么可能要交那么多税捏！明明我們比誰都善良守法……",
            "teller": "羅佳",
            "title": "9号罪人"
        },
        {
            "id": 16,
            "model": "돈키호테",
            "content": "吾一直活得堂堂正正！",
            "teller": "堂吉訶德",
            "title": "3号罪人"
        },
        {
            "id": 17,
            "model": "로쟈",
            "content": "没錯~！",
            "teller": "羅佳",
            "title": "9号罪人"
        },
        {
            "id": 18,
            "content": "就像听相声一様，維吉里烏斯静静地听着罪人們的喧鬧声，慢慢開口。"
        },
        {
            "id": 19,
            "model": "베르길리우스",
            "content": "対，正如袮們所説，100億眼的税款听起来確實不太合理。不過。",
            "teller": "維吉里烏斯",
            "title": "向導"
        },
        {
            "id": 20,
            "model": "베르길리우스",
            "content": "我還以為有人想得到捏，在道路中央挑起這種无意義的争斗会引発多大的麻煩。",
            "teller": "維吉里烏斯",
            "title": "向導"
        },
        {
            "id": 21,
            "model": "그레고르",
            "content": "唔……",
            "teller": "格里高尓",
            "title": "13号罪人"
        },
        {
            "id": 22,
            "model": "베르길리우스",
            "content": "哈啊……",
            "teller": "維吉里烏斯",
            "title": "向導"
        },
        {
            "id": 23,
            "content": "維吉里烏斯深深地嘆了口气，然后轉向了T公司的員工。"
        },
        {
            "id": 24,
            "model": "베르길리우스",
            "content": "対于這起事件引発的流血冲突，我們感到非常遺憾……",
            "teller": "維吉里烏斯",
            "title": "向導"
        },
        {
            "id": 25,
            "model": "베르길리우스",
            "content": "然而，高達100億眼的時間税……也實在譲人難以接受。",
            "teller": "維吉里烏斯",
            "title": "向導"
        },
        {
            "id": 26,
            "model": "베르길리우스",
            "content": "袮們肯定也清楚，如此巨額的征税不是輕易就能在街頭交付的。",
            "teller": "維吉里烏斯",
            "title": "向導"
        },
        {
            "id": 27,
            "model": "베르길리우스",
            "content": "比起這様突然来征收時間税，我覚得袮們應該先給我們解釋一下這数字是怎么来的。",
            "teller": "維吉里烏斯",
            "title": "向導"
        },
        {
            "id": 28,
            "model": "T사4등급",
            "teller": "4級征收人員",
            "title": "T公司",
            "content": "如此異常的征税报告實属罕見。我方也已意識到事態的厳重性，目前已在所属轄区辦公室召開緊急会議。"
        },
        {
            "id": 29,
            "model": "T사4등급",
            "teller": "4級征收人員",
            "title": "T公司",
            "content": "譲我們移步所属轄区的征收所，進一步討論此事発生的原因及解决方法叭。"
        }
    ]
}