{
  "dataList": [
    {
      "id": 0,
      "content": "T公司的某个餐庁。"
    },
    {
      "id": 1,
      "model": "돈키호테",
      "title": "T公司",
      "content": "天哪……諸位，請看看這牛排上滴落的肉汁！"
    },
    {
      "id": 2,
      "content": "孩子职场的同事中，有一人嘴中塞满了滴着肉汁的牛排并咀嚼着。"
    },
    {
      "id": 3,
      "teller": "2级征收人员",
      "title": "T公司",
      "content": "果然，来這里真是太好了。"
    },
    {
      "id": 4,
      "content": "坐在对面的另一位同事正愉悦地擦着嘴。"
    },
    {
      "id": 5,
      "content": "大家吃得都很享受，看上去是个不錯的餐庁。"
    },
    {
      "id": 6,
      "content": "但……孩子却一口也没吃，只是直直地看着餐叉上的牛排。"
    },
    {
      "id": 7,
      "model": "로쟈",
      "title": "T公司",
      "content": "真倒胃口……"
    },
    {
      "id": 8,
      "content": "那孩子肯定知晓這切好的牛排十分美味。"
    },
    {
      "id": 9,
      "content": "只是被夺走色彩的发黄牛排无法激起她的食欲。"
    },
    {
      "id": 10,
      "content": "那被夺去的色彩反而引起了陣陣反胃……"
    },
    {
      "id": 11,
      "content": "同时譲她的表情氷冷起来。"
    },
    {
      "id": 12,
      "content": "孩子带着不悦的眼神反复刺着牛排的碎块，而後深深地嘆了一口气并放下了餐叉。"
    },
    {
      "id": 13,
      "model": "돈키호테",
      "title": "T公司",
      "content": "罗佳，有何不適？僅就今日而言，汝之气色甚是不佳……"
    },
    {
      "id": 14,
      "model": "로쟈",
      "title": "T公司",
      "content": "没什么。只是……没有食欲罢了。"
    },
    {
      "id": 15,
      "model": "돈키호테",
      "title": "T公司",
      "content": "唔嗯~這可不妙！汝応借由此般美食来消解繁重职务的圧力！"
    },
    {
      "id": 16,
      "model": "돈키호테",
      "title": "T公司",
      "content": "来吧，就用這杯葡萄酒来干杯如何！"
    },
    {
      "id": 17,
      "model": "로쟈",
      "title": "T公司",
      "content": "……现在？现在才只到中午哦？"
    },
    {
      "id": 18,
      "model": "돈키호테",
      "title": "T公司",
      "content": "適量酒精对提升工作效率有所帮助！"
    },
    {
      "id": 19,
      "teller": "2级征收人员",
      "title": "T公司",
      "content": "的确如此。而且我们也不太有這种机会……"
    },
    {
      "id": 20,
      "content": "正如同事所言，等级不同的员工在這种餐庁中一起用餐的情況十分少见。"
    },
    {
      "id": 21,
      "content": "由于各自生活在不同的时間里，T公司的员工们大多和与自己时間相近的人一起吃飯。"
    },
    {
      "id": 22,
      "content": "為了创造一同進餐的机会，首先必須前往使用TT4协議的餐庁……"
    },
    {
      "id": 23,
      "content": "而那种地方，对时間并不富裕的低级员工来説負担很大。"
    },
    {
      "id": 24,
      "content": "所以他们為了尽可能減少負担，選择了来吃這些没有顔色的料理。"
    },
    {
      "id": 25,
      "content": "這个餐庁没有譲顔色复原的灯，所以价格也比較便宜。"
    },
    {
      "id": 26,
      "model": "로쟈",
      "title": "T公司",
      "content": "真是的，我明白了。干杯吧，干杯。"
    },
    {
      "id": 27,
      "content": "孩子不想破坏气氛，勉强地和同事碰了碰杯。"
    },
    {
      "id": 28,
      "content": "当然，玻璃杯里葡萄酒的顔色也同样譲孩子厌悪。"
    },
    {
      "id": 29,
      "content": "但她還是尽可能地，努力不将這种感情顕露在顔上。"
    },
    {
      "id": 30,
      "content": "当然，维持這种姿态并不容易……"
    },
    {
      "id": 31,
      "content": "孩子很快就从座位上離開了。"
    },
    {
      "id": 32,
      "content": "食物仍是一口未动。"
    },
    {
      "id": 33,
      "teller": "2级征收人员",
      "title": "T公司",
      "content": "已经要走了吗？"
    },
    {
      "id": 34,
      "model": "로쟈",
      "title": "T公司",
      "content": "最近是取缔違法发明行动期間吧~再不走的話我就趕不上时間了。"
    },
    {
      "id": 35,
      "model": "돈키호테",
      "title": "T公司",
      "content": "最近取缔工作十分繁重啊。有労了！"
    },
    {
      "id": 36,
      "model": "로쟈",
      "title": "T公司",
      "content": "哈哈……這样下去馬上就能晋升了吧？"
    },
    {
      "id": 37,
      "model": "로쟈",
      "title": "T公司",
      "content": "总之我先告辞了。"
    },
    {
      "id": 38,
      "teller": "2级征收人员",
      "title": "T公司",
      "content": "嗯……再见。"
    },
    {
      "id": 39,
      "content": "结束用餐之後，孩子去往的是T公司的後巷。"
    },
    {
      "id": 40,
      "content": "确認收到举报的地点，联络技术局，然後另行收集未登記的发明就是孩子今天的工作。"
    },
    {
      "id": 41,
      "model": "로쟈",
      "title": "T公司",
      "content": "未登記发明要全部没收。之後就是罚款了……"
    },
    {
      "id": 42,
      "model": "로쟈",
      "title": "T公司",
      "content": "根据本次更新的指南……這些每种8小时，合計需要缴纳40小时。没有不满吧？"
    },
    {
      "id": 43,
      "teller": "後巷的发明家",
      "title": "20区的居民",
      "content": "……40个小时！之前不是每种只用上缴7小时吗？"
    },
    {
      "id": 44,
      "model": "로쟈",
      "title": "T公司",
      "content": "最近罚款提高了呢~不服气吗？你想去征收所一項項地抗議吗？"
    },
    {
      "id": 45,
      "teller": "後巷的发明家",
      "title": "20区的居民",
      "content": "我没有……那种打算……"
    },
    {
      "id": 46,
      "content": "实際上，时間税并没有提高。"
    },
    {
      "id": 47,
      "content": "孩子只是，為了自己能够获取时間而索要了更多。"
    },
    {
      "id": 48,
      "content": "对T公司低等级的征收人员来説，获取的时間很少是常态。"
    },
    {
      "id": 49,
      "content": "收取比応当征收的更多的时間，那之間的差値就能作為自己的时間来使用。"
    },
    {
      "id": 50,
      "content": "如果无謂地争吵、被盯上了就可能被以各种理由征收更多时間，所以T公司的市民都睁一只眼閉一只眼。"
    },
    {
      "id": 51,
      "model": "로쟈",
      "title": "T公司",
      "content": "因為来的是我，所以交這么多就够了~要是来的是其他时間征收人员，至少会每項收你10个小时吧。"
    },
    {
      "id": 52,
      "teller": "後巷的发明家",
      "title": "20区的居民",
      "content": "……"
    },
    {
      "id": 53,
      "model": "로쟈",
      "title": "T公司",
      "content": "還有，把手从表上拿開。"
    },
    {
      "id": 54,
      "content": "察覚发明家将手搭上了腰間的鐘表，孩子立馬制止了他。"
    },
    {
      "id": 55,
      "content": "就算拥有再多时間，在当天立刻使用自己所拥有的时間也是不可能的……"
    },
    {
      "id": 56,
      "content": "但若是前一天予先留存了时間，就可以通過触碰鐘表来進行加速。"
    },
    {
      "id": 57,
      "content": "但是对方想要取出的，并不是鐘表。"
    },
    {
      "id": 58,
      "model": "로쟈",
      "title": "T公司",
      "content": "工具！？"
    },
    {
      "id": 59,
      "teller": "後巷的发明家",
      "title": "20区的居民",
      "content": "哎，罢了。反正我也没有能交给征收人的时間。"
    },
    {
      "id": 60,
      "content": "随着对方从腰間取出工具，从後巷四处也陸続出现了手持工具的人们。"
    },
    {
      "id": 61,
      "content": "看来他从最開始就没有缴纳罚款的打算。"
    },
    {
      "id": 62,
      "model": "로쟈",
      "title": "T公司",
      "content": "哎呀，你什么时候叫了這么多朋友過来？"
    },
    {
      "id": 63,
      "teller": "後巷的发明家",
      "title": "20区的居民",
      "content": "要是被收走40个小时，我就要過一周每天只有4个小时的生活了。那還能叫人的生活吗？"
    },
    {
      "id": 64,
      "model": "로쟈",
      "title": "T公司",
      "content": "至少能保障4个小时不是很好吗。"
    },
    {
      "id": 65,
      "content": "孩子对突然出现的人感到了些許惊讶，但迅速冷静下来開始扭転手表的发条。"
    },
    {
      "id": 66,
      "content": "随着发条転动的声音，孩子的身体也開始浮现残像般的痕迹。"
    },
    {
      "id": 67,
      "content": "那是配备给T公司征收人员的标配型鐘表。"
    },
    {
      "id": 68,
      "content": "要是把执行任务用的时間全部用完了，接下来就只能使用自己的时間了……"
    },
    {
      "id": 69,
      "content": "但孩子還是選择了租賃时間。"
    },
    {
      "id": 70,
      "model": "로쟈",
      "title": "T公司",
      "content": "雖然把這些时間用在你们身上十分浪費……嗯，也没办法。"
    },
    {
      "id": 71,
      "content": "没有回答。"
    },
    {
      "id": 72,
      "content": "不，准确来説是回答得太慢了。"
    },
    {
      "id": 73,
      "content": "人群不断挥打着武器与工具，却毫无意义。"
    },
    {
      "id": 74,
      "content": "无論来自哪个方向的攻击，在已经身处更多时間里的孩子眼中都十分遅缓。"
    },
    {
      "id": 75,
      "content": "随着时間增加，动作也变得迅捷的孩子踏出的每一步，都譲对手的顔上逐渐浮现出恐惧。"
    },
    {
      "id": 76,
      "model": "로쟈",
      "title": "T公司",
      "content": "雖然你们听不见我在説什么，但還是先説好。"
    },
    {
      "id": 77,
      "model": "로쟈",
      "title": "T公司",
      "content": "浪費我时間的代价。做好加倍偿還的准备吧。"
    }
  ]
}