{
    "dataList": [
        {
            "id": 0,
            "model": "돈키호테",
            "teller": "堂吉訶德",
            "title": "Cinq協会 東部3科",
            "content": "唔~這様真的可以麼？吾現在正在用餐捏……"
        },
        {
            "id": 1,
            "teller": "記者",
            "title": "？？？",
            "content": "協会的各位應該都很忙碌叭。我最担心的反而是我的采訪会不会占用宁的用餐時間。"
        },
        {
            "id": 2,
            "model": "돈키호테",
            "teller": "堂吉訶德",
            "title": "Cinq協会 東部3科",
            "content": "嗚，那様的話完全不用担心！看到汝這般礼貌，恐怕很少会有人拒絶叭！"
        },
        {
            "id": 3,
            "content": "孩子一辺開着玩笑一辺重新握起了快子。"
        },
        {
            "id": 4,
            "content": "他露出満懐期待的表情，挟起了熱气騰騰的面条和蔬菜……"
        },
        {
            "id": 5,
            "teller": "？？？",
            "title": "？？？",
            "content": "給老子站住！"
        },
        {
            "id": 6,
            "content": "在他背后，木制的椅子和餐具正朝着某个方向飛去。"
        },
        {
            "id": 7,
            "model": "돈키호테",
            "teller": "堂吉訶德",
            "title": "Cinq協会 東部3科",
            "content": "唔。用餐帰用餐，但是在如此喧鬧的客桟里，吾也会担心汝是否会受傷捏。"
        },
        {
            "id": 8,
            "teller": "記者",
            "title": "？？？",
            "content": "那里的話，這種事何止一兩次捏。対記者来説是家常便飯了。"
        },
        {
            "id": 9,
            "teller": "記者",
            "title": "？？？",
            "content": "我也是从小在協会附属的健身房里鍛錬長大的，所以這種事也没那么可怕。"
        },
        {
            "id": 10,
            "model": "돈키호테",
            "teller": "堂吉訶德",
            "title": "Cinq協会 東部3科",
            "content": "嚇……頗有胆識啊，汝？啊！那辺頭頂，当心！"
        },
        {
            "id": 11,
            "teller": "記者",
            "title": "？？？",
            "content": "呵呵。呼，多謝宁。"
        },
        {
            "id": 12,
            "model": "돈키호테",
            "teller": "堂吉訶德",
            "title": "Cinq協会 東部3科",
            "content": "甚好……吾很欣賞汝！吾，定将知无不言。尽管問叭！"
        },
        {
            "id": 13,
            "content": "只看平静交談着的孩子和記者的様子的話，説不定会以為這是某个平和的地方……"
        },
        {
            "id": 14,
            "content": "那兩人雖然一点也不在乎，但周圍却被破坏得很厳重，尖鋭漕雑的争炒声不絶于耳。"
        },
        {
            "id": 15,
            "content": "……如果没有偶尓躱避一下朝自己飛来的東西的動作，簡直看不出這間客桟已經被卷入到一場混戦之中了。"
        },
        {
            "id": 16,
            "teller": "記者",
            "title": "？？？",
            "content": "這次我們雑志打算将Cinq協会作為特輯报道……"
        },
        {
            "id": 17,
            "teller": "記者",
            "title": "？？？",
            "content": "其中，我們想着重説明Cinq協会各个支部的区別。"
        },
        {
            "id": 18,
            "model": "돈키호테",
            "teller": "堂吉訶德",
            "title": "Cinq協会 東部3科",
            "content": "唔唔！近来，西部和南部的Cinq似乎很受媒体重視捏。"
        },
        {
            "id": 19,
            "teller": "記者",
            "title": "？？？",
            "content": "啊，宁平時喜歓看雑志和报紙麼？"
        },
        {
            "id": 20,
            "model": "돈키호테",
            "teller": "堂吉訶德",
            "title": "Cinq協会 東部3科",
            "content": "那是当然！作為收尾人，理應対世事保持関注不是麼？"
        },
        {
            "id": 21,
            "content": "孩子心里想着只読收尾人相関的报道就劬了……但他决定不把這一段説出口。"
        },
        {
            "id": 22,
            "content": "因為已經積累了相当多的經驗，所以他覚得説那些多余的話没有什么帮助。"
        },
        {
            "id": 23,
            "teller": "記者",
            "title": "？？？",
            "content": "真帥呀……然后，想問宁几个問題。"
        },
        {
            "id": 24,
            "teller": "記者",
            "title": "？？？",
            "content": "我听説Cinq協会本部所在的西部和東部的行動宗旨相当不同，宁認為具体有那些差異捏？"
        },
        {
            "id": 25,
            "model": "돈키호테",
            "teller": "堂吉訶德",
            "title": "Cinq協会 東部3科",
            "content": "唔~吾雖然没有親自去過本部……不過，听聞之事還是不少的。"
        },
        {
            "id": 26,
            "model": "돈키호테",
            "teller": "堂吉訶德",
            "title": "Cinq協会 東部3科",
            "content": "听説那辺必須随身携帯剣。都是些関于用剣的礼儀之類的，似乎被很多規矩限制着捏。"
        },
        {
            "id": 27,
            "model": "돈키호테",
            "teller": "堂吉訶德",
            "title": "Cinq協会 東部3科",
            "content": "東部就自由很多了。可以使用武器，也可以不用……啊，不過比起剣，吾更青來凭身体肉搏。"
        },
        {
            "id": 28,
            "content": "孩子一辺説着，一辺舉起手腕展示。"
        },
        {
            "id": 29,
            "content": "他手腕上佩戴着的用玉雕琢成的厚重手鏈，閃耀着玲瓏剔透的光澤。"
        },
        {
            "id": 30,
            "teller": "記者",
            "title": "？？？",
            "content": "啊啊……！這就是那个所謂的翠炎玉器麼？"
        },
        {
            "id": 31,
            "model": "돈키호테",
            "teller": "堂吉訶德",
            "title": "Cinq協会 東部3科",
            "content": "汝知道的真不少！正是，這手鏈能使吾之手套変得炙熱。大多数東西，只要握住就能直接融化掉。"
        },
        {
            "id": 32,
            "teller": "記者",
            "title": "？？？",
            "content": "所以宁才不抛手套啊……"
        },
        {
            "id": 33,
            "model": "돈키호테",
            "teller": "堂吉訶德",
            "title": "Cinq協会 東部3科",
            "content": "啊哈，汝是在説本部那辺的决斗申請麼？"
        },
        {
            "id": 34,
            "model": "돈키호테",
            "teller": "堂吉訶德",
            "title": "Cinq協会 東部3科",
            "content": "東部的做法有些許不同。比起抛東西出去，鄭重地报上姓名与所属并擺好架勢，才是决斗開始的象征。"
        },
        {
            "id": 35,
            "teller": "記者",
            "title": "？？？",
            "content": "確實，我也經常見到那様的做法。"
        },
        {
            "id": 36,
            "model": "돈키호테",
            "teller": "堂吉訶德",
            "title": "Cinq協会 東部3科",
            "content": "西部和南部的習俗，也別有一番風趣捏~"
        },
        {
            "id": 37,
            "teller": "記者",
            "title": "？？？",
            "content": "……不過話説回来。"
        },
        {
            "id": 38,
            "model": "돈키호테",
            "teller": "堂吉訶德",
            "title": "Cinq協会 東部3科",
            "content": "呵呀，這實在是太美味了……唔？汝説什么？"
        },
        {
            "id": 39,
            "teller": "記者",
            "title": "？？？",
            "content": "因為宁从剛才開始就一直在抖腿……我在想是不是出什么問題了。"
        },
        {
            "id": 40,
            "model": "돈키호테",
            "teller": "堂吉訶德",
            "title": "Cinq協会 東部3科",
            "content": "問題？什、什么都没有！哈哈，只是吾之習慣罷了！"
        },
        {
            "id": 41,
            "teller": "記者",
            "title": "？？？",
            "content": "可是宁看起来有些着急捏……"
        },
        {
            "id": 42,
            "model": "돈키호테",
            "teller": "堂吉訶德",
            "title": "Cinq協会 東部3科",
            "content": "啊……哈哈……咳咳。"
        },
        {
            "id": 43,
            "content": "實際上孩子是有些着急。"
        },
        {
            "id": 44,
            "content": "説是心煩意乱可能更准確一些。"
        },
        {
            "id": 45,
            "content": "身辺起了争端，目睹着有人被単方面欺凌的光景……自己却只能坐在那里，什么也做不了。"
        },
        {
            "id": 46,
            "content": "以他的本性而言……他会以“正義”之名，代替被欺凌的人出頭。"
        },
        {
            "id": 47,
            "content": "然而Cinq協会的本質始終是决斗的代理……所以。"
        },
        {
            "id": 48,
            "model": "돈키호테",
            "teller": "堂吉訶德",
            "title": "Cinq協会 東部3科",
            "content": "那、那是因為吾覚得……差不多……應該会有人委托吾来進行决斗代理了……"
        },
        {
            "id": 49,
            "model": "돈키호테",
            "teller": "堂吉訶德",
            "title": "Cinq協会 東部3科",
            "content": "有一点……叭？感覚有点晚了叭。"
        },
        {
            "id": 50,
            "teller": "記者",
            "title": "？？？",
            "content": "……啊？"
        },
        {
            "id": 51,
            "model": "돈키호테",
            "teller": "堂吉訶德",
            "title": "Cinq協会 東部3科",
            "content": "不，何以言之？目睹到那般単方面的争斗，難道不会坐立不安手痒難耐麼？"
        },
        {
            "id": 52,
            "teller": "記者",
            "title": "？？？",
            "content": "哦……宁原来是想去打架麼？"
        },
        {
            "id": 53,
            "model": "돈키호테",
            "teller": "堂吉訶德",
            "title": "Cinq協会 東部3科",
            "content": "怎能説得如此輕率！實力不均衡的戦斗，根本毫无正義可言叭。"
        },
        {
            "id": 54,
            "model": "돈키호테",
            "teller": "堂吉訶德",
            "title": "Cinq協会 東部3科",
            "content": "然身為協会的一員，如果没有任何委托的話……是不能劬出手的……"
        },
        {
            "id": 55,
            "content": "孩子的声音似乎在漸漸変得消沈。"
        },
        {
            "id": 56,
            "content": "然后，記者似乎从孩子的言語中，回憶起了某个熟悉的声音。"
        },
        {
            "id": 57,
            "teller": "記者",
            "title": "？？？",
            "content": "説起来，我有听説過几年前有一个剛加入Cinq協会的人，做了類似義警的事情……"
        },
        {
            "id": 58,
            "model": "돈키호테",
            "teller": "堂吉訶德",
            "title": "Cinq協会 東部3科",
            "content": "啊咳、咳咳！咳……那、那時与現在不同啊！"
        },
        {
            "id": 59,
            "model": "돈키호테",
            "teller": "堂吉訶德",
            "title": "Cinq協会 東部3科",
            "content": "吾已經変了！不会喊着不義就直接冲過去了，現在已經能劬像這様穏……穏重地等候了！"
        },
        {
            "id": 60,
            "content": "匡！"
        },
        {
            "id": 61,
            "content": "也許，就像躱避飛来的家具時一様……這也只是个失誤叭。"
        },
        {
            "id": 62,
            "content": "自以為占了上風的暴徒拔出了剣，却被滾落脚辺的木片絆倒了。"
        },
        {
            "id": 63,
            "content": "但是，那个失誤偏偏朝着孩子的方向倒了過去……"
        },
        {
            "id": 64,
            "model": "돈키호테",
            "teller": "堂吉訶德",
            "title": "Cinq協会 東部3科",
            "content": "而且！像這種利刃飛向吾的情况，吾不是依然能保持冷静麼！"
        },
        {
            "id": 65,
            "content": "孩子習慣性地握住了刀刃。"
        },
        {
            "id": 66,
            "teller": "？？？",
            "title": "？？？",
            "content": "什……啊？！C、Cinq……"
        },
        {
            "id": 67,
            "content": "翠炎玉器閃過強烈的光輝，随后那刀刃就像融化的糖果般流淌而下了。"
        },
        {
            "id": 68,
            "model": "돈키호테",
            "teller": "堂吉訶德",
            "title": "Cinq協会 東部3科",
            "content": "好了，既然都到這一步了那差不多也該……対叭！"
        },
        {
            "id": 69,
            "content": "這幅光景吸引了在場所有人的視綫，到剛才為止一直都在被単方面欺凌的人慌張地砲了過来，対孩子喊道。"
        },
        {
            "id": 70,
            "teller": "？？？",
            "title": "？？？",
            "content": "C、Cinq大人！委托、請接受我的委托！"
        },
        {
            "id": 71,
            "model": "돈키호테",
            "teller": "堂吉訶德",
            "title": "Cinq協会 東部3科",
            "content": "唔！甚好。只是這種“緊急委托”可是要收汝双倍的价銭哦？"
        },
        {
            "id": 72,
            "teller": "？？？",
            "title": "？？？",
            "content": "三倍也无所謂！只要能把那个混蛋……"
        },
        {
            "id": 73,
            "model": "돈키호테",
            "teller": "堂吉訶德",
            "title": "Cinq協会 東部3科",
            "content": "OK！！成交！之后再議。"
        },
        {
            "id": 74,
            "content": "孩子像收到了圣誕礼物般，難以掩飾興奮的表情，猛地从座位上站起身来。"
        },
        {
            "id": 75,
            "model": "돈키호테",
            "teller": "堂吉訶德",
            "title": "Cinq協会 東部3科",
            "content": "吾乃，Cinq協会東部3科！"
        },
        {
            "id": 76,
            "model": "돈키호테",
            "teller": "堂吉訶德",
            "title": "Cinq協会 東部3科",
            "content": "就由吾堂吉訶德……接續這場决斗！"
        }
    ]
}