{
    "dataList": [
        {
            "id": 0,
            "place": "LCE研究組 走廊",
            "model": "단테",
            "content": "<還是没有信号麼？>",
            "teller": "但丁",
            "title": "執行經理"
        },
        {
            "id": 1,
            "model": "그레고르",
            "content": "……対。都没辦法掌握大家的情况，真是……",
            "teller": "格里高尓",
            "title": "13号罪人"
        },
        {
            "id": 2,
            "model": "그레고르",
            "content": "算了，也没什么大事叭……都説没消息就是最好的消息嘛。",
            "teller": "格里高尓",
            "title": "13号罪人"
        },
        {
            "id": 3,
            "model": "이상",
            "content": "阿莉莎女士……我仍心懐牽挂。須在那支螺旋更加深入前尽快尋得綫索……",
            "teller": "李箱",
            "title": "1号罪人"
        },
        {
            "id": 4,
            "model": "검지제자2",
            "content": "螺旋……麼？",
            "teller": "空",
            "title": "LCE研究組"
        },
        {
            "id": 5,
            "model": "검지제자2",
            "content": "啊，是指那个工坊生産的武器麼？没有密碼就没辦法解開的那个！",
            "teller": "空",
            "title": "LCE研究組"
        },
        {
            "id": 6,
            "model": "이상",
            "content": "正是……實属一大難題。",
            "teller": "李箱",
            "title": "1号罪人"
        },
        {
            "id": 7,
            "model": "검지제자2",
            "content": "唔……原、原理我雖然了解，但是密碼只有刺下去的本人知道。不、不過我也会尽力帮忙調査的！",
            "teller": "空",
            "title": "LCE研究組"
        },
        {
            "id": 8,
            "model": "이상",
            "content": "……",
            "teller": "李箱",
            "title": "1号罪人"
        },
        {
            "id": 9,
            "model": "료슈",
            "content": "……",
            "teller": "良秀",
            "title": "4号罪人"
        },
        {
            "id": 10,
            "model": "그레고르",
            "content": "哦，那可帮上大忙了。不過，空小姐好像対工坊装備很感興趣啊？",
            "teller": "格里高尓",
            "title": "13号罪人"
        },
        {
            "id": 11,
            "model": "검지제자2",
            "content": "是的！很早以前就開始感興趣了。説不定我正是因為這个才来到這里的。",
            "teller": "空",
            "title": "LCE研究組"
        },
        {
            "id": 12,
            "model": "라비",
            "content": "唔……？那比起LCE，L……",
            "teller": "拉維",
            "title": "LCE事務組"
        },
        {
            "id": 13,
            "model": "료슈",
            "content": "喂，新来的。",
            "teller": "良秀",
            "title": "4号罪人"
        },
        {
            "id": 14,
            "model": "라비",
            "content": "是？",
            "teller": "拉維",
            "title": "LCE事務組"
        },
        {
            "id": 15,
            "model": "료슈",
            "content": "當住我視野了。退后点。",
            "teller": "良秀",
            "title": "4号罪人"
        },
        {
            "id": 16,
            "model": "라비",
            "content": "啊……不好意思。",
            "teller": "拉維",
            "title": "LCE事務組"
        },
        {
            "id": 17,
            "model": "단테",
            "content": "<……？>",
            "teller": "但丁",
            "title": "執行經理"
        },
        {
            "id": 18,
            "content": "因為良秀厳粛的指示，拉維一臉乾介地退后了。"
        },
        {
            "id": 19,
            "content": "換做平常……不管是格里高尓還是李箱……大概都会念叨兩句“不要対第一次見面的人説這種話”之類的，但現在大概是情况不同。"
        },
        {
            "id": 20,
            "content": "兩人平静地看着后退的拉維，随后不動声色地向前邁了一步。"
        },
        {
            "id": 21,
            "model": "그레고르",
            "content": "那空小姐，我們一辺走一辺聊聊工坊制品叭。別看我們這様，対工坊確實是知道得不多。",
            "teller": "格里高尓",
            "title": "13号罪人"
        },
        {
            "id": 22,
            "model": "검지제자2",
            "content": "真、真的麼？太好了。我，很喜歓聊天。",
            "teller": "空",
            "title": "LCE研究組"
        },
        {
            "id": 23,
            "model": "라비",
            "content": "我也很喜歓聊天的……",
            "teller": "拉維",
            "title": "LCE事務組"
        },
        {
            "id": 24,
            "model": "이상",
            "content": "啊，是叫拉維叭。看来袮也懐有研究者的天性，対新生技術頗具関心。",
            "teller": "李箱",
            "title": "1号罪人"
        },
        {
            "id": 25,
            "model": "이상",
            "content": "袮不妨与我們經理暫做交談。",
            "teller": "李箱",
            "title": "1号罪人"
        },
        {
            "id": 26,
            "model": "단테",
            "content": "<為什么……？>",
            "teller": "但丁",
            "title": "執行經理"
        },
        {
            "id": 27,
            "model": "라비",
            "content": "為什么……？",
            "teller": "拉維",
            "title": "LCE事務組"
        },
        {
            "id": 28,
            "model": "이상",
            "content": "哦，我很高興但丁也同意了。来叭，我們三人相聚，想必能進行一番深奥的学術探討。",
            "teller": "李箱",
            "title": "1号罪人"
        },
        {
            "id": 29,
            "content": "不知怎么莫名被卷入李箱突然組建的学術会里的我，現在正走在格里高尓和名為空的人身后一步左右的地方。"
        },
        {
            "id": 30,
            "model": "검지제자2",
            "content": "各、各位対這様的我還這么親、親切，真的很感謝。",
            "teller": "空",
            "title": "LCE研究組"
        },
        {
            "id": 31,
            "model": "검지제자2",
            "content": "我喜歓親、親切的人。因為我的同事們都不這様。所、所以我經常游离在外。這次也是，要是在想別、別的事情的時候一个人落后于隊伍了，一定会被欺負的。",
            "teller": "空",
            "title": "LCE研究組"
        },
        {
            "id": 32,
            "model": "그레고르",
            "content": "怎么会捏，再怎么説也不会把幸存的研究員一个人抛下叭……？不過，反正也没把作戦整个稿匝，也算合格叭。",
            "teller": "格里高尓",
            "title": "13号罪人"
        },
        {
            "id": 33,
            "model": "단테",
            "content": "<就是啊……>",
            "teller": "但丁",
            "title": "執行經理"
        },
        {
            "id": 34,
            "content": "一想起我們至今為止稿匝的計劃，准確来説是至今為止稿匝的索德的計劃，我的心情就変得復雑起来。"
        },
        {
            "id": 35,
            "model": "검지제자2",
            "content": "啊。這、這位就是各位的領導者麼。",
            "teller": "空",
            "title": "LCE研究組"
        },
        {
            "id": 36,
            "model": "료슈",
            "content": "真没眼光。",
            "teller": "良秀",
            "title": "4号罪人"
        },
        {
            "id": 37,
            "model": "단테",
            "content": "<……是想説我不値得信頼麼？>",
            "teller": "但丁",
            "title": "執行經理"
        },
        {
            "id": 38,
            "model": "료슈",
            "content": "呵。是説袮不只是个領導者，而是超越領導者的存在。",
            "teller": "良秀",
            "title": "4号罪人"
        },
        {
            "id": 39,
            "content": "……雖然我不覚得良秀是真心這么説的，但姑且還是帯着微妙的心情点了点頭。"
        },
        {
            "id": 40,
            "model": "이상",
            "content": "唔。深感賛同。",
            "teller": "李箱",
            "title": "1号罪人"
        },
        {
            "id": 41,
            "model": "검지제자2",
            "content": "果然，但、但丁宁就是領導者叭。",
            "teller": "空",
            "title": "LCE研究組"
        },
        {
            "id": 42,
            "model": "검지제자2",
            "content": "領、領導者……我覚得就是應該由不知道在想什么的人来当。",
            "teller": "空",
            "title": "LCE研究組"
        },
        {
            "id": 43,
            "model": "검지제자2",
            "content": "難以捉摸的人不是很、很帥嘛。",
            "teller": "空",
            "title": "LCE研究組"
        },
        {
            "id": 44,
            "model": "단테",
            "content": "<是、是麼？>",
            "teller": "但丁",
            "title": "執行經理"
        },
        {
            "id": 45,
            "model": "그레고르",
            "content": "怎么還害羞了。",
            "teller": "格里高尓",
            "title": "13号罪人"
        },
        {
            "id": 46,
            "model": "검지제자2",
            "content": "我、我也覚得那様很帥，所以才决定加入這里的。原本我是在其、其他事務所的，應該算是被掘角了叭。",
            "teller": "空",
            "title": "LCE研究組"
        },
        {
            "id": 47,
            "model": "이상",
            "content": "掘角……原来如此，我們十二人也正是被浮士德女士掘角而来。",
            "teller": "李箱",
            "title": "1号罪人"
        },
        {
            "id": 48,
            "model": "이상",
            "content": "良秀女士，袮是否也从浮士德女士之処……得到過某種約定？",
            "teller": "李箱",
            "title": "1号罪人"
        },
        {
            "id": 49,
            "model": "료슈",
            "content": "没錯。",
            "teller": "良秀",
            "title": "4号罪人"
        },
        {
            "id": 50,
            "model": "이상",
            "content": "雖感羞耻……但既然往日已逝，我也直言即可。",
            "teller": "李箱",
            "title": "1号罪人"
        },
        {
            "id": 51,
            "model": "이상",
            "content": "我仍无法発自内心相信……浮士德女士所言之事終有成功之時。",
            "teller": "李箱",
            "title": "1号罪人"
        },
        {
            "id": 52,
            "model": "이상",
            "content": "那時的言語倣佛梦想。",
            "teller": "李箱",
            "title": "1号罪人"
        },
        {
            "id": 53,
            "model": "이상",
            "content": "若我能更加確信，或許便不会如黯然沈寂般度過往日歳月……",
            "teller": "李箱",
            "title": "1号罪人"
        },
        {
            "id": 54,
            "model": "이상",
            "content": "而袮，自踏上巴士那日起……似乎从未懐疑浮士德女士所言之事。",
            "teller": "李箱",
            "title": "1号罪人"
        },
        {
            "id": 55,
            "model": "료슈",
            "content": "……嗤。",
            "teller": "良秀",
            "title": "4号罪人"
        },
        {
            "id": 56,
            "model": "그레고르",
            "content": "這么一説……現在回想起来，看上去最容易出岔子的人反而是完成工作最利索的那个？",
            "teller": "格里高尓",
            "title": "13号罪人"
        },
        {
            "id": 57,
            "content": "仔細想来，良秀雖然總是一副興致缺缺被迫工作的様子，但却一次都没有因不満而抱怨過。"
        },
        {
            "id": 58,
            "content": "就算是因為契約……但那怕有一点対實現愿望的懐疑，應該都不会這様跟随我和維吉里烏斯了叭……"
        },
        {
            "id": 59,
            "model": "료슈",
            "content": "我也不是一開始就相信。",
            "teller": "良秀",
            "title": "4号罪人"
        },
        {
            "id": 60,
            "model": "료슈",
            "content": "只是不得不相信。",
            "teller": "良秀",
            "title": "4号罪人"
        },
        {
            "id": 61,
            "model": "료슈",
            "content": "那个白発的……",
            "teller": "良秀",
            "title": "4号罪人"
        },
        {
            "id": 62,
            "model": "료슈",
            "content": "他当時是這么説的：",
            "teller": "良秀",
            "title": "4号罪人"
        },
        {
            "id": 63,
            "model": "료슈",
            "content": "“竟然……”",
            "teller": "良秀",
            "title": "4号罪人"
        },
        {
            "id": 64,
            "place": -1,
            "model": "파우스트",
            "title": "？？？",
            "content": "竟然……",
            "teller": "浮士德"
        },
        {
            "id": 65,
            "model": "파우스트",
            "title": "？？？",
            "content": "還没有被切断捏。那根細綫。",
            "teller": "浮士德"
        },
        {
            "id": 66,
            "model": "과거료슈3",
            "content": "……袮看到了什么才這么説。",
            "teller": "<size=50%><voffset=0.3em>Yoshihide</voffset></size>\n良秀",
            "title": "蜘蛛巢"
        },
        {
            "id": 67,
            "model": "파우스트",
            "title": "？？？",
            "content": "袮被斬，以及被袮所斬之人流下的血……正因它們沾染其上，才能勾勒出如此鮮明的紅綫。",
            "teller": "浮士德"
        },
        {
            "id": 68,
            "model": "파우스트",
            "title": "？？？",
            "content": "那是……只有袮才能打開的空間。即使是在蜘蛛网中央，他們也无法将其打開。",
            "teller": "浮士德"
        },
        {
            "id": 69,
            "model": "파우스트",
            "title": "？？？",
            "content": "在如此情形下，可以説袮做出了明智的選擇。",
            "teller": "浮士德"
        },
        {
            "id": 70,
            "model": "과거료슈3",
            "content": "……",
            "teller": "<size=50%><voffset=0.3em>Yoshihide</voffset></size>\n良秀",
            "title": "蜘蛛巢"
        },
        {
            "id": 71,
            "model": "과거료슈3",
            "content": "誰雇袮来的？",
            "teller": "<size=50%><voffset=0.3em>Yoshihide</voffset></size>\n良秀",
            "title": "蜘蛛巢"
        },
        {
            "id": 72,
            "model": "과거료슈3",
            "content": "袮以為如今連父輩都能斬下并离開的我，還斬不了袮那三寸之舌麼？",
            "teller": "<size=50%><voffset=0.3em>Yoshihide</voffset></size>\n良秀",
            "title": "蜘蛛巢"
        },
        {
            "id": 73,
            "model": "파우스트",
            "title": "？？？",
            "content": "我明白。袮是一辺斬断自己的脳海一辺抵達這里的。如果我和袮的目的略有相悖，袮便会毫不犹豫地斬殺我。",
            "teller": "浮士德"
        },
        {
            "id": 74,
            "model": "파우스트",
            "title": "？？？",
            "content": "如今袮将孩子藏匿在了誰也无法打開的場所之中，因而只能等待将其取回的那天。",
            "teller": "浮士德"
        },
        {
            "id": 75,
            "model": "파우스트",
            "title": "？？？",
            "content": "時間想必不長不短叭。為了安全起見，旋鈕應該設置在五年以内叭。",
            "teller": "浮士德"
        },
        {
            "id": 76,
            "model": "과거료슈3",
            "content": "……",
            "teller": "<size=50%><voffset=0.3em>Yoshihide</voffset></size>\n良秀",
            "title": "蜘蛛巢"
        },
        {
            "id": 77,
            "model": "파우스트",
            "title": "？？？",
            "content": "如果和我一起走，那么兩年内便能鏟除蜘蛛巢，譲袮与女儿重逢。",
            "teller": "浮士德"
        },
        {
            "id": 78,
            "model": "과거료슈3",
            "content": "這是契約麼？作為代价，我要殺誰？",
            "teller": "<size=50%><voffset=0.3em>Yoshihide</voffset></size>\n良秀",
            "title": "蜘蛛巢"
        },
        {
            "id": 79,
            "model": "파우스트",
            "title": "？？？",
            "content": "……",
            "teller": "浮士德"
        },
        {
            "id": 80,
            "model": "파우스트",
            "title": "？？？",
            "content": "不是殺戮，而是拯救。",
            "teller": "浮士德"
        },
        {
            "id": 81,
            "model": "과거료슈3",
            "content": "拯救？",
            "teller": "<size=50%><voffset=0.3em>Yoshihide</voffset></size>\n良秀",
            "title": "蜘蛛巢"
        },
        {
            "id": 82,
            "model": "파우스트",
            "title": "？？？",
            "content": "直面罪孼……",
            "teller": "浮士德"
        },
        {
            "id": 83,
            "model": "파우스트",
            "title": "？？？",
            "content": "拯救自我。",
            "teller": "浮士德"
        },
        {
            "id": 84,
            "model": "파우스트",
            "title": "？？？",
            "content": "這是袮，在這辺獄公司里需要記住的第一句話。",
            "teller": "浮士德"
        },
        {
            "id": 85,
            "model": "과거료슈3",
            "content": "……真暈。",
            "teller": "<size=50%><voffset=0.3em>Yoshihide</voffset></size>\n良秀",
            "title": "蜘蛛巢"
        },
        {
            "id": 86,
            "model": "파우스트",
            "title": "？？？",
            "content": "因為太難了麼？",
            "teller": "浮士德"
        },
        {
            "id": 87,
            "model": "과거료슈3",
            "content": "……是因為久違地抽了烟。",
            "teller": "<size=50%><voffset=0.3em>Yoshihide</voffset></size>\n良秀",
            "title": "蜘蛛巢"
        },
        {
            "id": 88,
            "place": "LCE研究組 走廊",
            "model": "단테",
            "content": "<……>",
            "teller": "但丁",
            "title": "執行經理"
        },
        {
            "id": 89,
            "model": "단테",
            "content": "<女儿藏在……安全的地方了麼？>",
            "teller": "但丁",
            "title": "執行經理"
        },
        {
            "id": 90,
            "model": "료슈",
            "content": "没錯。",
            "teller": "良秀",
            "title": "4号罪人"
        },
        {
            "id": 91,
            "model": "료슈",
            "content": "那里面……几乎不受外界時間的影響。",
            "teller": "良秀",
            "title": "4号罪人"
        },
        {
            "id": 92,
            "model": "단테",
            "content": "<不受時間影響……是運用T公司奇点制作的麼？>",
            "teller": "但丁",
            "title": "執行經理"
        },
        {
            "id": 93,
            "model": "료슈",
            "content": "没錯。我親自驗証了許多次。",
            "teller": "良秀",
            "title": "4号罪人"
        },
        {
            "id": 94,
            "model": "료슈",
            "content": "在支离破碎的記憶之間還清晰留存着。我重復了上百次的實驗与誓言。",
            "teller": "良秀",
            "title": "4号罪人"
        },
        {
            "id": 95,
            "model": "료슈",
            "content": "因此我堅信時間一到，无論是蜘蛛巢順着纏繞在我身上的這些絲綫前来找我，還是我沿着這絲綫回到蜘蛛巢。只要這段記憶未被遺忘，只要那人的契約仍然有效……",
            "teller": "良秀",
            "title": "4号罪人"
        },
        {
            "id": 96,
            "model": "단테",
            "content": "<唔，契約……一定会履行的。>",
            "teller": "但丁",
            "title": "執行經理"
        }
    ]
}