{
    "dataList": [
        {
            "id": 0,
            "place": "当鋪街",
            "model": "파우스트",
            "content": "請譲我説明此次計劃。",
            "teller": "浮士德",
            "title": "2号罪人"
        },
        {
            "id": 1,
            "model": "파우스트",
            "content": "為了到達金枝所在之処，首要任務是所有人不被懐疑地潜入賭場。",
            "teller": "浮士德",
            "title": "2号罪人"
        },
        {
            "id": 2,
            "model": "파우스트",
            "content": "根据我們調査到的信息，入口共有三个。",
            "teller": "浮士德",
            "title": "2号罪人"
        },
        {
            "id": 3,
            "model": "파우스트",
            "content": "一个供普通訪客出入的門，一个是只有VIP才能使用的専用通道，而最后一个是供員工使用的后門。",
            "teller": "浮士德",
            "title": "2号罪人"
        },
        {
            "id": 4,
            "model": "파우스트",
            "content": "我們每組各負責一个入口……四人假扮賭場荷官，四人假扮普通客人，其余四人則假扮VIP客人，然后分頭潜入。",
            "teller": "浮士德",
            "title": "2号罪人"
        },
        {
            "id": 5,
            "model": "오티스",
            "content": "確實，越集体行動越引人注目。",
            "teller": "奥提斯",
            "title": "12号罪人"
        },
        {
            "id": 6,
            "model": "이상",
            "content": "与其聚集一処，不如分散而行。",
            "teller": "李箱",
            "title": "1号罪人"
        },
        {
            "id": 7,
            "model": "파우스트",
            "content": "請打開分発的信封以確認自己負責扮演的角色。",
            "teller": "浮士德",
            "title": "2号罪人"
        },
        {
            "id": 8,
            "model": "파우스트",
            "content": "此外，如果此次作戦仍未能回收金枝，",
            "teller": "浮士德",
            "title": "2号罪人"
        },
        {
            "id": 9,
            "model": "파우스트",
            "content": "高層将担心今后的計劃也会出現顕著問題。",
            "teller": "浮士德",
            "title": "2号罪人"
        },
        {
            "id": 10,
            "model": "파우스트",
            "content": "因此，這次我們将展開聯合作戦。",
            "teller": "浮士德",
            "title": "2号罪人"
        },
        {
            "id": 11,
            "model": "단테",
            "content": "<聯合？>",
            "teller": "但丁",
            "title": "執行經理"
        },
        {
            "id": 12,
            "model": "파우스트",
            "content": "我們的搭档是由更専業和更熟練的人員組成的辺獄公司特別部隊……",
            "teller": "浮士德",
            "title": "2号罪人"
        },
        {
            "id": 13,
            "model": "파우스트",
            "content": "他們現在被称為LCC，清理部門。在潜入作戦方面，他們比我們更加優秀。",
            "teller": "浮士德",
            "title": "2号罪人"
        },
        {
            "id": 14,
            "model": "이스마엘",
            "content": "我還以為現在人就已經劬多了捏。",
            "teller": "以實瑪利",
            "title": "8号罪人"
        },
        {
            "id": 15,
            "model": "그레고르",
            "content": "看来有人終于意識到人数并不重要了。",
            "teller": "格里高尓",
            "title": "13号罪人"
        },
        {
            "id": 16,
            "model": "홍루",
            "content": "哇！我還是第一次見其他部門的人員捏。他們在那儿捏？",
            "teller": "鴻璐",
            "title": "6号罪人"
        },
        {
            "id": 17,
            "content": "鴻璐環顧四周，或許是期待着浮士德立刻从什么地方把他們帯出来自我介紹。"
        },
        {
            "id": 18,
            "content": "……当然，他東張西望了一会儿也没人出現。"
        },
        {
            "id": 19,
            "model": "파우스트",
            "content": "我們将前往一間当鋪。",
            "teller": "浮士德",
            "title": "2号罪人"
        },
        {
            "id": 20,
            "model": "그레고르",
            "content": "現在還有這種店鋪麼？",
            "teller": "格里高尓",
            "title": "13号罪人"
        },
        {
            "id": 21,
            "model": "파우스트",
            "content": "這里被称作当鋪街，大多数店鋪都兼営典当生意。",
            "teller": "浮士德",
            "title": "2号罪人"
        },
        {
            "id": 22,
            "model": "파우스트",
            "content": "那家店就是会合地点。進去叭。",
            "teller": "浮士德",
            "title": "2号罪人"
        }
    ]
}