{
    "dataList": [
        {
            "id": "cultivation_rewardShopButton",
            "content": "奨励兌換"
        },
        {
            "id": "cultivation_missionbutton_normal",
            "content": "成就"
        },
        {
            "id": "cultivation_missionbutton_not_clear",
            "content": "通過8.5-3"
        },
        {
            "id": "cultivation_classbutton_normal",
            "content": "養成"
        },
        {
            "id": "cultivation_classbutton_not_clear",
            "content": "進入8.5-4"
        },
        {
            "id": "cultivation_stagebutton_normal",
            "content": "関峠"
        },
        {
            "id": "cultivation_stagebutton_not_clear",
            "content": "通過8-33"
        },
        {
            "id": "cultivation_stagebutton_end_event",
            "content": "活動結束"
        },
        {
            "id": "cultivation_bonus_preview",
            "content": "活動加成角色"
        },
        {
            "id": "cultivation_storybutton_before_start",
            "content": "通過8.5-1"
        },
        {
            "id": "cultivation_storybutton_normal",
            "content": "跳轉至放映室"
        },
        {
            "id": "cultivation_bonus_popup_title",
            "content": "活動加成角色"
        },
        {
            "id": "cultivation_bonusUI_Desc",
            "content": "活動期間，当編隊中包含以下人格時，<color=#ffa7a7>[智·勇·仁基礎入門手册]</color>的獲取量将提升。\n獲取量提升合計最大値為<color=#ffa7a7>120%</color>。"
        },
        {
            "id": "cultivation_scrap_guide_title",
            "content": "活動道具介紹"
        },
        {
            "id": "cultivation_rewardpage_desc",
            "content": "通関活動関峠后，将獲得<color=#ffa7a7>[智·勇·仁基礎入門手册]</color>。\n此外，在首次通関主綫関峠及清剿鏡像迷宮時，也可獲得<color=#ffa7a7>[智·勇·仁基礎入門手册]</color>。\n\n在通関活動、主綫関峠及清剿鏡像迷宮時有小概率可以獲得<color=#ffa7a7>[假装不是秘籍的秘籍]</color>，獲得時，<color=#ffa7a7>[假装不是秘籍的秘籍]</color>将会自動轉換為20个<color=#ffa7a7>[智·勇·仁基礎入門手册]</color>。\n\n宁可以在<color=#ffa7a7>[奨励兌換]</color>処根据所持有的<color=#ffa7a7>[智·勇·仁基礎入門手册]</color>数量兌換各種奨励。"
        },
        {
            "id": "cultivation_reward_popup_desc",
            "content": "通関活動関峠、\n首次通関主綫劇情関峠、以及通関鏡像迷宮時，\n可獲得<color=#ffa7a7>[智·勇·仁基礎入門手册]</color>。\n\n可在<color=#ffa7a7>[奨励兌換]</color>窗口中花費<color=#ffa7a7>[智·勇·仁基礎入門手册]</color>，\n以獲得各種各様的奨励。"
        },
        {
            "id": "cultivation_mission_reward_popup_desc",
            "content": "授課過程中可達成各種成就。\n達成時可獲得<color=#ffa7a7>[智·勇·仁基礎入門手册]</color>。\n\n活動結束后无法継續達成成就，但仍可領取奨励。"
        },
        {
            "id": "ask_xichun_class_node_enter",
            "content": "要進入教室継續授課麼？"
        },
        {
            "id": "not_playing_xichun_class_node",
            "content": "授課還未開始。"
        },
        {
            "id": "not_playing_xichun_class_node_retry",
            "content": "授課已結束。\n若想重新開始授課，請从関峠8.5-4進入。"
        }
    ]
}