{
    "dataList": [
        {
            "id": 1092,
            "panicName": "混雑的記憶",
            "lowMoraleDescription": "回合開始時，使自身獲得1~3層[AttackUp]并対自身施加1~3層[DefenseDown]",
            "panicDescription": "回合開始時，使自身獲得1~5層[AttackUp]并対自身施加1~5層[DefenseDown]"
        },
        {
            "id": 1093,
            "panicName": "怨恨",
            "lowMoraleDescription": "- 回合開始時，使自身獲得1層[Enhancement]并対自身施加1層[Disarming]\n- 回合結束時，下回合使自身獲得2層[Agility]",
            "panicDescription": "- 回合開始時，使自身獲得2層[Enhancement]并対自身施加2層[Disarming]\n- 回合結束時，下回合使自身獲得2層[Agility]"
        },
        {
            "id": 1094,
            "panicName": "対情报的執念",
            "lowMoraleDescription": "- 与帯有[TakePicture]的目標進行拼点時，使自身的基礎威力+1，造成的傷害+10%\n- 回合開始時，対自身施加1層[Vulnerable]",
            "panicDescription": "- 与帯有[TakePicture]的目標進行拼点時，使自身的基礎威力+1，造成的傷害+20%\n- 回合開始時，対自身施加2層[Vulnerable]"
        },
        {
            "id": 1095,
            "panicName": "沈溺的悔恨",
            "lowMoraleDescription": "- 回合開始時，対自身施加2層[AttackDmgDown]并使自身恢復40点体力",
            "panicDescription": "- 回合開始時，対自身施加3層[AttackDmgDown]并使自身恢復60点体力"
        },
        {
            "id": 1096,
            "panicName": "顕影的記憶",
            "lowMoraleDescription": "対自身施加1層[Vulnerable]，使自身造成的傷害+10%，暴撃時造成的傷害+15%",
            "panicDescription": "対自身施加2層[Vulnerable]，使自身造成的傷害+10%，暴撃時造成的傷害+30%，<color=#ff6000><mark color=#ff000040><b><u>令本国弓[肉]-放箭的硬幣施加的状態效果変為2倍</color></mark></b></u>"
        }
    ]
}