{
  "dataList": [
    {
      "id": "get_10405_1",
      "desc": "获得人格",
      "dlg": "荒谬。竟然譲我去当·保。"
    },
    {
      "id": "lobby_morning_10405_1",
      "desc": "早間問候",
      "dlg": "好好听早課……別惹麻烦。"
    },
    {
      "id": "lobby_noon_10405_1",
      "desc": "午間問候",
      "dlg": "午飯……？自·吃。光是在這时候出門就够譲人心烦了。"
    },
    {
      "id": "lobby_night_10405_1",
      "desc": "晚間問候",
      "dlg": "晚上了……不久後，列車就会到站。终于有点有意思的了。"
    },
    {
      "id": "smalltalk_10405_1",
      "desc": "对話 1",
      "dlg": "“只是清理、打扫列車”……哈，這可不僅僅是清扫。而是一种芸术。"
    },
    {
      "id": "smalltalk_10405_2",
      "desc": "对話 2",
      "dlg": "每当車門打開的时候，便有形形色色的芸术品在迎接我。能有机会観摩数千年間沉淀而成的美学，只是想象一下都能譲人感到心潮澎湃，不是吗？"
    },
    {
      "id": "smalltalk_10405_3",
      "desc": "对話 3",
      "dlg": "我本応該全身心投入到列車清扫工作里，却突然負責起什么新人培訓……喂，你去和上头的説説。"
    },
    {
      "id": "smalltalk_10405_4",
      "desc": "同步後对話 1",
      "dlg": "偶尔……未经彫琢的芸术品会四处乱走。那些大多是許多乗客融在一起後的样子。\n我覚得那姿态本身就十分美妙……但最後還是要把它们剥開……令人遺憾。"
    },
    {
      "id": "smalltalk_10405_5",
      "desc": "同步後对話 2",
      "dlg": "工作中最精彩的一点吗……当然能説了。那就是，芸术品们完全不曾想過自己坐上列車就会变成芸术品這一点。\n不，也不是不知道……応該説是他们没想知道。這种讽刺是最妙的。"
    },
    {
      "id": "neglect_10405_1",
      "desc": "閑置",
      "dlg": "呼……這該死的等待什么时候结束。我已经不耐烦了……"
    },
    {
      "id": "gacksung_10405_1",
      "desc": "進行同步",
      "dlg": "哼，如果你認同我的实力，那就不該把我分配去管理人员，而是進行现场清扫。"
    },
    {
      "id": "formation_10405_1",
      "desc": "人格出战",
      "dlg": "终于到现场工作了。"
    },
    {
      "id": "battleentry_10405_1",
      "desc": "進入战斗",
      "dlg": "清扫时間到了。"
    },
    {
      "id": "battle_select_10405_1",
      "desc": "战斗中選中人格",
      "dlg": "別打断我。现在正是……好时候呢。"
    },
    {
      "id": "battle_endcommand_10405_1",
      "desc": "進行攻击",
      "dlg": "我会将作品刻于你眼中。"
    },
    {
      "id": "battle_enemy_break_10405_1",
      "desc": "敌方混乱",
      "dlg": "就要完成了吗……"
    },
    {
      "id": "battle_break_10405_1",
      "desc": "自身混乱",
      "dlg": "哈。"
    },
    {
      "id": "battle_kill_10405_1",
      "desc": "击杀敌方",
      "dlg": "收笔。"
    },
    {
      "id": "battle_dead_10405_1",
      "desc": "自身陣亡",
      "dlg": "哈，這也是……相当前卫啊……"
    },
    {
      "id": "choice_success_p_10405_2",
      "desc": "判定成功",
      "dlg": "没·問。"
    },
    {
      "id": "choice_fail_n_10405_1",
      "desc": "判定失敗",
      "dlg": "妈·的。"
    },
    {
      "id": "battle_clear_10405_1",
      "desc": "战斗胜利",
      "dlg": "還不赖……那么，等下一班列車来吧。"
    },
    {
      "id": "battle_clear_ex_10405_1",
      "desc": "EX CLEAR战斗胜利",
      "dlg": "精彩的展覧。哈，我是不是該对他们説感激不尽？"
    },
    {
      "id": "battle_defeat_10405_1",
      "desc": "战斗失敗",
      "dlg": "真惨烈。……不对，被降职的話我不就能做更多现场工作了吗？"
    }
  ]
}