{
  "dataList": [
    {
      "id": "get_10703_1",
      "desc": "获得人格",
      "dlg": "嘻嘻哈哈……蹦蹦跳跳……兔子躍来，粉碎一切！"
    },
    {
      "id": "lobby_morning_10703_1",
      "desc": "早間問候",
      "dlg": "啥？第一次见早起出来洗顔的兔子吗？"
    },
    {
      "id": "lobby_noon_10703_1",
      "desc": "午間問候",
      "dlg": "有没有不錯的任务？想一想就譲人热血沸腾又眼红的那种……火热的作战。"
    },
    {
      "id": "lobby_night_10703_1",
      "desc": "晚間問候",
      "dlg": "雖然看起来不像，但我其实是夜行性动物。也就是説越黒暗，我就越敏捷。"
    },
    {
      "id": "smalltalk_10703_1",
      "desc": "对話 1",
      "dlg": "我説！与其在這里百无聊赖地唠嗑不如再派一个任务。"
    },
    {
      "id": "smalltalk_10703_2",
      "desc": "对話 2",
      "dlg": "我是兔子。哪里有新鮮草，我便要去哪。"
    },
    {
      "id": "smalltalk_10703_3",
      "desc": "对話 3",
      "dlg": "是誰説兔子弱小来着？要是碰上一群饥飢的兔子，你覚得接下来都会发生些什么？"
    },
    {
      "id": "smalltalk_10703_4",
      "desc": "同步後对話 1",
      "dlg": "如果我打着打着連着哥们你也一起干了的話也別怨我。兔子天性如此。"
    },
    {
      "id": "smalltalk_10703_5",
      "desc": "同步後对話 2",
      "dlg": "你那鐘表头還挺有用的，有没有考虑過一起加入兔子隊蹦蹦跳跳啊？"
    },
    {
      "id": "neglect_10703_1",
      "desc": "閑置",
      "dlg": "知道吗？兔子的耳朵，很灵敏。"
    },
    {
      "id": "gacksung_10703_1",
      "desc": "進行同步",
      "dlg": "就這么做，早該這样了！"
    },
    {
      "id": "formation_10703_1",
      "desc": "人格出战",
      "dlg": "好，是該撕咬新鮮草的时候了。"
    },
    {
      "id": "battleentry_10703_1",
      "desc": "進入战斗",
      "dlg": "发现了新鮮嫩的青草！"
    },
    {
      "id": "battle_select_10703_1",
      "desc": "战斗中選中人格",
      "dlg": "想到什么火热的計划了吗？"
    },
    {
      "id": "battle_endcommand_10703_1",
      "desc": "進行攻击",
      "dlg": "蹦蹦跳跳！"
    },
    {
      "id": "battle_enemy_break_10703_1",
      "desc": "敌方混乱",
      "dlg": "再蹦跶一个試試啊！"
    },
    {
      "id": "battle_break_10703_1",
      "desc": "自身混乱",
      "dlg": "哈……！"
    },
    {
      "id": "battle_kill_10703_1",
      "desc": "击杀敌方",
      "dlg": "呼，還挺有嚼劲。"
    },
    {
      "id": "battle_allydead_10703_1",
      "desc": "友方陣亡",
      "dlg": "寂寞了吗？這么快就死掉了。"
    },
    {
      "id": "choice_success_p_10703_1",
      "desc": "判定成功",
      "dlg": "小菜一碟。"
    },
    {
      "id": "choice_fail_n_10703_1",
      "desc": "判定失敗",
      "dlg": "我都照做了。不满意就向上级投訴啊。"
    },
    {
      "id": "battle_clear_10703_1",
      "desc": "战斗胜利",
      "dlg": "怎样？是不是强到爆炸還快得離谱？"
    },
    {
      "id": "battle_clear_ex_10703_1",
      "desc": "EX CLEAR战斗胜利",
      "dlg": "我的肌肉兴奋得颤抖！還有没有找打的？這才刚開始！"
    },
    {
      "id": "battle_defeat_10703_1",
      "desc": "战斗失敗",
      "dlg": "没时間休息了。立刻再次出击！"
    }
  ]
}