{
    "dataList": [
        {
            "id": 1067,
            "panicName": "紊乱的呼吸",
            "lowMoraleDescription": "回合開始時，使自身減少3級[Breath]強度",
            "panicDescription": "回合開始時，使自身減少5級[Breath]強度"
        },
        {
            "id": 1068,
            "panicName": "教材",
            "lowMoraleDescription": "与帯有[DuelEdge]的目標拼点時，拼点威力+1\n拼点失敗時，下回合対自身施加1層[Vulnerable](每回合最多1次)",
            "panicDescription": "与帯有[DuelEdge]的目標拼点時，拼点威力+2\n拼点失敗時，下回合対自身施加2層[Vulnerable](每回合最多1次)"
        },
        {
            "id": 1069,
            "panicName": "鉄処女",
            "lowMoraleDescription": "回合開始時，対自身施加1層[AttackDown]并使自身獲得1層[DefenseUp]",
            "panicDescription": "回合開始時，対自身施加2層[AttackDown]并使自身獲得2層[DefenseUp]"
        }
    ]
}