{
    "dataList": [
        {
            "id": 0,
            "content": "第15日！"
        },
        {
            "id": 1,
            "content": "今日亦是何等忙碌的一日！"
        },
        {
            "id": 2,
            "content": "雖然被分配到培訓部以来只過了四天，但吾的日程表已經被填満了。"
        },
        {
            "id": 3,
            "content": "雖然每天總会有一兩名新人加入我們部門，但由于第二天就見不到他們了……似乎也没有閑暇去記住他們的臉。"
        },
        {
            "id": 4,
            "content": "不過~部門之間人員的派遣和交換也是常有的事，新人們一定是被分配到了更适合他們的崗位上了叭！"
        },
        {
            "id": 5,
            "content": "吾，今天也対O-04-84……不、不対。対小提灯進行工作。"
        },
        {
            "id": 6,
            "content": "啊，准確地来説，小提灯又砲到走廊的某処去開花了！"
        },
        {
            "id": 7,
            "content": "吾，為了把小提灯再次帯回收容単元，有必要進行工作。"
        },
        {
            "id": 8,
            "content": "吾多次警告它不要一声不吭就開始玩捉迷藏……但它就是不听吾的話。"
        },
        {
            "id": 9,
            "content": "与其他異想体不同，小提灯即使出逃也不会響起特殊警报。"
        },
        {
            "id": 10,
            "content": "吾注意到它出逃……是作為小提灯専属員工的吾，在確認到收容単元正空着的同時，突然有区域的員工失踪报告増加了的時候。"
        },
        {
            "id": 11,
            "content": "吾注意到這点并迅速敢往可疑区域后……小提灯一定藏在這里。"
        },
        {
            "id": 12,
            "content": "它肯定随便選了一个收容単元的門口，正開着花……并一口把一无所知的新人員工当作肥料呑下，吾无法放任此等惡行発生！"
        },
        {
            "id": 13,
            "content": "无可奈何下，吾只能用几記脳瓜崩教訓一下這位朋友……然后把它送回了收容単元。"
        },
        {
            "id": 14,
            "content": "然后……吾完成了預定的工作。"
        },
        {
            "id": 15,
            "content": "原本的計劃的清潔工作和收容単元内的光照強度調整測試也已經完成了……但果然還是應該為今天出逃這件事厳歴地斥責小提灯！"
        },
        {
            "id": 16,
            "content": "啊……但是。"
        },
        {
            "id": 17,
            "content": "請想想看叭！怎么能随意叱責那个蓬蓬軟軟的孩子捏？"
        },
        {
            "id": 18,
            "content": "竟然只用稍微用力一点的撫摸那些毛来代替訓誡……吾也考慮過吾的内心是不是也太軟弱了。"
        },
        {
            "id": 19,
            "content": "无所謂了……当吾从收容単元出来，目視着PE-BOX被傳送時……"
        },
        {
            "id": 20,
            "content": "差不多是時候了叭，出現考驗的警报響徹了整个公司！"
        },
        {
            "id": 21,
            "content": "奥提斯女士……不，奥提斯隊長還在收容単元中工作。所以不能参加考驗的應対。初期應対好像是失敗了，然后又有几个收容単元被損坏了。"
        },
        {
            "id": 22,
            "content": "砲到走廊中的朋友里……啊啊，也有吾之前負責過的旧友，小宇宙！"
        },
        {
            "id": 23,
            "content": "它給了吾如此可愛的愛心型徽章当礼物，我却不得不用脳瓜崩教訓它，稍稍有些心痛。"
        },
        {
            "id": 24,
            "content": "但是……工作就是工作！公司正是信任着吾才把工作交給吾的！"
        },
        {
            "id": 25,
            "content": "若這是吾所被分配的工作，那吾定将以歓愉迎之！"
        },
        {
            "id": 26,
            "content": "而吾也必将如此。"
        },
        {
            "id": 27,
            "content": "今天的日記，到此為止！"
        }
    ]
}